{
"meta":{"test_sets":[],"test_metrics":[],"learn_metrics":[{"best_value":"Min","name":"Logloss"}],"launch_mode":"Train","parameters":"","iteration_count":1000,"learn_sets":["learn"],"name":"experiment"},
"iterations":[
{"learn":[0.6612421625],"iteration":0,"passed_time":0.004285449479,"remaining_time":4.28116403},
{"learn":[0.6310436507],"iteration":1,"passed_time":0.008778640371,"remaining_time":4.380541545},
{"learn":[0.6032957949],"iteration":2,"passed_time":0.01300472222,"remaining_time":4.321902683},
{"learn":[0.5775935587],"iteration":3,"passed_time":0.01761952327,"remaining_time":4.387261295},
{"learn":[0.551879447],"iteration":4,"passed_time":0.02206690513,"remaining_time":4.391314121},
{"learn":[0.5308487347],"iteration":5,"passed_time":0.02651153432,"remaining_time":4.392077518},
{"learn":[0.5115600404],"iteration":6,"passed_time":0.03078431898,"remaining_time":4.366975535},
{"learn":[0.4912591511],"iteration":7,"passed_time":0.03535832703,"remaining_time":4.384432552},
{"learn":[0.4752565497],"iteration":8,"passed_time":0.03978522447,"remaining_time":4.380795272},
{"learn":[0.4591084307],"iteration":9,"passed_time":0.04438939504,"remaining_time":4.394550109},
{"learn":[0.4418354133],"iteration":10,"passed_time":0.04892344988,"remaining_time":4.398662903},
{"learn":[0.4273837476],"iteration":11,"passed_time":0.05337626188,"remaining_time":4.394645562},
{"learn":[0.4112457052],"iteration":12,"passed_time":0.0582843796,"remaining_time":4.425129435},
{"learn":[0.3999198393],"iteration":13,"passed_time":0.06293473476,"remaining_time":4.432403462},
{"learn":[0.3880063492],"iteration":14,"passed_time":0.06761622064,"remaining_time":4.440131822},
{"learn":[0.3757691898],"iteration":15,"passed_time":0.07248889722,"remaining_time":4.458067179},
{"learn":[0.3668447685],"iteration":16,"passed_time":0.07736858637,"remaining_time":4.47372473},
{"learn":[0.3571498304],"iteration":17,"passed_time":0.08187873322,"remaining_time":4.466939779},
{"learn":[0.3480842646],"iteration":18,"passed_time":0.08642275458,"remaining_time":4.462143276},
{"learn":[0.3415811078],"iteration":19,"passed_time":0.09101151306,"remaining_time":4.45956414},
{"learn":[0.3337662619],"iteration":20,"passed_time":0.09567115034,"remaining_time":4.460097913},
{"learn":[0.3276174104],"iteration":21,"passed_time":0.1002856086,"remaining_time":4.458151146},
{"learn":[0.3213279759],"iteration":22,"passed_time":0.1051603214,"remaining_time":4.467027568},
{"learn":[0.3179052664],"iteration":23,"passed_time":0.1097879566,"remaining_time":4.464710235},
{"learn":[0.3147006128],"iteration":24,"passed_time":0.1143080958,"remaining_time":4.458015736},
{"learn":[0.3099721025],"iteration":25,"passed_time":0.1192244665,"remaining_time":4.466331937},
{"learn":[0.3042332055],"iteration":26,"passed_time":0.1240353871,"remaining_time":4.469867841},
{"learn":[0.2989678974],"iteration":27,"passed_time":0.1287878825,"remaining_time":4.470779351},
{"learn":[0.2956408714],"iteration":28,"passed_time":0.1336367047,"remaining_time":4.474525527},
{"learn":[0.2914913589],"iteration":29,"passed_time":0.1384667109,"remaining_time":4.477090319},
{"learn":[0.2869825754],"iteration":30,"passed_time":0.1432455161,"remaining_time":4.477577582},
{"learn":[0.2838168692],"iteration":31,"passed_time":0.1480003249,"remaining_time":4.477009829},
{"learn":[0.2808839281],"iteration":32,"passed_time":0.1528362409,"remaining_time":4.478564999},
{"learn":[0.2766728016],"iteration":33,"passed_time":0.1575044427,"remaining_time":4.474979167},
{"learn":[0.2733472574],"iteration":34,"passed_time":0.1622185959,"remaining_time":4.472598429},
{"learn":[0.2701086727],"iteration":35,"passed_time":0.1669224177,"remaining_time":4.469811408},
{"learn":[0.2667260747],"iteration":36,"passed_time":0.1715332943,"remaining_time":4.464501687},
{"learn":[0.2636992531],"iteration":37,"passed_time":0.17623049,"remaining_time":4.461413982},
{"learn":[0.2615148726],"iteration":38,"passed_time":0.1810717941,"remaining_time":4.46179472},
{"learn":[0.2589851696],"iteration":39,"passed_time":0.1858779215,"remaining_time":4.461070117},
{"learn":[0.2568169488],"iteration":40,"passed_time":0.1905899035,"remaining_time":4.457944327},
{"learn":[0.2547525533],"iteration":41,"passed_time":0.1953225915,"remaining_time":4.455215302},
{"learn":[0.2519582983],"iteration":42,"passed_time":0.1999135351,"remaining_time":4.449238444},
{"learn":[0.2507460667],"iteration":43,"passed_time":0.2043523019,"remaining_time":4.440018196},
{"learn":[0.2491203969],"iteration":44,"passed_time":0.208820949,"remaining_time":4.431644584},
{"learn":[0.2469463399],"iteration":45,"passed_time":0.2136229507,"remaining_time":4.430354239},
{"learn":[0.2450356795],"iteration":46,"passed_time":0.2184447486,"remaining_time":4.429315861},
{"learn":[0.2439686361],"iteration":47,"passed_time":0.2229182386,"remaining_time":4.421211733},
{"learn":[0.2426260001],"iteration":48,"passed_time":0.2278077204,"remaining_time":4.42132943},
{"learn":[0.2409576089],"iteration":49,"passed_time":0.2323167656,"remaining_time":4.414018547},
{"learn":[0.2394078486],"iteration":50,"passed_time":0.2370606028,"remaining_time":4.41118651},
{"learn":[0.2384005252],"iteration":51,"passed_time":0.2416719856,"remaining_time":4.4058662},
{"learn":[0.236471178],"iteration":52,"passed_time":0.2464116558,"remaining_time":4.402864869},
{"learn":[0.2346839956],"iteration":53,"passed_time":0.2511293135,"remaining_time":4.399413529},
{"learn":[0.2336323516],"iteration":54,"passed_time":0.2557403162,"remaining_time":4.394083614},
{"learn":[0.2325307196],"iteration":55,"passed_time":0.2604531784,"remaining_time":4.390496436},
{"learn":[0.2313273842],"iteration":56,"passed_time":0.2652566805,"remaining_time":4.388369292},
{"learn":[0.2300697721],"iteration":57,"passed_time":0.270086372,"remaining_time":4.386575214},
{"learn":[0.2293818062],"iteration":58,"passed_time":0.2758112544,"remaining_time":4.398955769},
{"learn":[0.2285343516],"iteration":59,"passed_time":0.2805635126,"remaining_time":4.395495031},
{"learn":[0.2275059493],"iteration":60,"passed_time":0.2854988227,"remaining_time":4.394809746},
{"learn":[0.2266925464],"iteration":61,"passed_time":0.2907537808,"remaining_time":4.398823329},
{"learn":[0.225453638],"iteration":62,"passed_time":0.2956392722,"remaining_time":4.397047589},
{"learn":[0.2247795918],"iteration":63,"passed_time":0.3004005859,"remaining_time":4.393358568},
{"learn":[0.2239517113],"iteration":64,"passed_time":0.3057600497,"remaining_time":4.398240716},
{"learn":[0.2229757024],"iteration":65,"passed_time":0.3109880468,"remaining_time":4.400952057},
{"learn":[0.2215864412],"iteration":66,"passed_time":0.3163267834,"remaining_time":4.404968491},
{"learn":[0.2205533972],"iteration":67,"passed_time":0.3212184186,"remaining_time":4.402581855},
{"learn":[0.2197737183],"iteration":68,"passed_time":0.3262764686,"remaining_time":4.402368004},
{"learn":[0.2191824137],"iteration":69,"passed_time":0.3311608044,"remaining_time":4.39970783},
{"learn":[0.2185786121],"iteration":70,"passed_time":0.3359975629,"remaining_time":4.396362478},
{"learn":[0.2175736583],"iteration":71,"passed_time":0.3407711084,"remaining_time":4.392160952},
{"learn":[0.2171181467],"iteration":72,"passed_time":0.3456444038,"remaining_time":4.389210443},
{"learn":[0.2162703543],"iteration":73,"passed_time":0.3501894416,"remaining_time":4.382100309},
{"learn":[0.2158094269],"iteration":74,"passed_time":0.3547207854,"remaining_time":4.374889686},
{"learn":[0.2154313304],"iteration":75,"passed_time":0.359606672,"remaining_time":4.372060065},
{"learn":[0.2148798361],"iteration":76,"passed_time":0.3644554471,"remaining_time":4.368732178},
{"learn":[0.214313333],"iteration":77,"passed_time":0.3694336744,"remaining_time":4.366895485},
{"learn":[0.2138317395],"iteration":78,"passed_time":0.3744358166,"remaining_time":4.365258064},
{"learn":[0.2132738071],"iteration":79,"passed_time":0.3793072146,"remaining_time":4.362032968},
{"learn":[0.2127191199],"iteration":80,"passed_time":0.3842030592,"remaining_time":4.359044586},
{"learn":[0.2124008535],"iteration":81,"passed_time":0.3890586148,"remaining_time":4.355558639},
{"learn":[0.2119656639],"iteration":82,"passed_time":0.3938934473,"remaining_time":4.351810737},
{"learn":[0.2115101511],"iteration":83,"passed_time":0.39881521,"remaining_time":4.348984909},
{"learn":[0.2110363706],"iteration":84,"passed_time":0.4038729357,"remaining_time":4.347573367},
{"learn":[0.2106722506],"iteration":85,"passed_time":0.4086417952,"remaining_time":4.343006986},
{"learn":[0.2099103687],"iteration":86,"passed_time":0.4137253422,"remaining_time":4.341738361},
{"learn":[0.2095402915],"iteration":87,"passed_time":0.4183907659,"remaining_time":4.336049756},
{"learn":[0.2089963413],"iteration":88,"passed_time":0.4230842881,"remaining_time":4.330671758},
{"learn":[0.2085119403],"iteration":89,"passed_time":0.4278183126,"remaining_time":4.325718494},
{"learn":[0.2080744235],"iteration":90,"passed_time":0.432437975,"remaining_time":4.319627685},
{"learn":[0.2076424419],"iteration":91,"passed_time":0.4369891096,"remaining_time":4.312892517},
{"learn":[0.2071686491],"iteration":92,"passed_time":0.4420131694,"remaining_time":4.310816609},
{"learn":[0.2068416637],"iteration":93,"passed_time":0.4468419815,"remaining_time":4.306796119},
{"learn":[0.2064568672],"iteration":94,"passed_time":0.4515467237,"remaining_time":4.301576684},
{"learn":[0.2062007618],"iteration":95,"passed_time":0.4561635067,"remaining_time":4.295539688},
{"learn":[0.2059565351],"iteration":96,"passed_time":0.4607958513,"remaining_time":4.289676842},
{"learn":[0.2054898808],"iteration":97,"passed_time":0.4654264789,"remaining_time":4.283823306},
{"learn":[0.2051838396],"iteration":98,"passed_time":0.4704068867,"remaining_time":4.281177827},
{"learn":[0.2049862362],"iteration":99,"passed_time":0.4752360253,"remaining_time":4.277124228},
{"learn":[0.2046301887],"iteration":100,"passed_time":0.480110855,"remaining_time":4.273461966},
{"learn":[0.2042419438],"iteration":101,"passed_time":0.4848318603,"remaining_time":4.268421672},
{"learn":[0.2040227399],"iteration":102,"passed_time":0.4894836926,"remaining_time":4.262785168},
{"learn":[0.203792199],"iteration":103,"passed_time":0.4943510559,"remaining_time":4.259024481},
{"learn":[0.203550994],"iteration":104,"passed_time":0.4989970489,"remaining_time":4.253355798},
{"learn":[0.2029990497],"iteration":105,"passed_time":0.5038810435,"remaining_time":4.249713706},
{"learn":[0.2028010835],"iteration":106,"passed_time":0.5084113135,"remaining_time":4.243096289},
{"learn":[0.2026158423],"iteration":107,"passed_time":0.5131155915,"remaining_time":4.2379547},
{"learn":[0.2021421673],"iteration":108,"passed_time":0.5178311967,"remaining_time":4.232913727},
{"learn":[0.2017572713],"iteration":109,"passed_time":0.522748418,"remaining_time":4.229509927},
{"learn":[0.2013805569],"iteration":110,"passed_time":0.527601866,"remaining_time":4.225568098},
{"learn":[0.2010351878],"iteration":111,"passed_time":0.5327320344,"remaining_time":4.223803987},
{"learn":[0.2008042948],"iteration":112,"passed_time":0.5376064415,"remaining_time":4.219972687},
{"learn":[0.2004643113],"iteration":113,"passed_time":0.5425945393,"remaining_time":4.217006683},
{"learn":[0.199887951],"iteration":114,"passed_time":0.5474777611,"remaining_time":4.213198423},
{"learn":[0.1995098416],"iteration":115,"passed_time":0.5523325884,"remaining_time":4.209155242},
{"learn":[0.1991830929],"iteration":116,"passed_time":0.5574475155,"remaining_time":4.207061164},
{"learn":[0.1988498319],"iteration":117,"passed_time":0.562212242,"remaining_time":4.202298283},
{"learn":[0.1986429072],"iteration":118,"passed_time":0.5673052214,"remaining_time":4.199965547},
{"learn":[0.1984047334],"iteration":119,"passed_time":0.5719344406,"remaining_time":4.194185897},
{"learn":[0.1980027836],"iteration":120,"passed_time":0.576918585,"remaining_time":4.191003605},
{"learn":[0.1976549355],"iteration":121,"passed_time":0.5816905279,"remaining_time":4.186264619},
{"learn":[0.1973509108],"iteration":122,"passed_time":0.5864440698,"remaining_time":4.181393896},
{"learn":[0.1971136651],"iteration":123,"passed_time":0.5912147492,"remaining_time":4.176646131},
{"learn":[0.1967226145],"iteration":124,"passed_time":0.5959514955,"remaining_time":4.171660468},
{"learn":[0.1965009817],"iteration":125,"passed_time":0.6006046727,"remaining_time":4.166099079},
{"learn":[0.1962939442],"iteration":126,"passed_time":0.6053122339,"remaining_time":4.160925829},
{"learn":[0.196000396],"iteration":127,"passed_time":0.6101142928,"remaining_time":4.15640362},
{"learn":[0.1957617195],"iteration":128,"passed_time":0.6148907517,"remaining_time":4.151704223},
{"learn":[0.1954101208],"iteration":129,"passed_time":0.6197891747,"remaining_time":4.147819861},
{"learn":[0.1951380621],"iteration":130,"passed_time":0.624778174,"remaining_time":4.144520864},
{"learn":[0.1948545639],"iteration":131,"passed_time":0.6297517122,"remaining_time":4.141094592},
{"learn":[0.1944547758],"iteration":132,"passed_time":0.6350026329,"remaining_time":4.139453253},
{"learn":[0.1941447987],"iteration":133,"passed_time":0.6402186168,"remaining_time":4.137532255},
{"learn":[0.1938467554],"iteration":134,"passed_time":0.6457493757,"remaining_time":4.137579333},
{"learn":[0.1935068514],"iteration":135,"passed_time":0.6508552818,"remaining_time":4.13484532},
{"learn":[0.1933047947],"iteration":136,"passed_time":0.6562471234,"remaining_time":4.133877865},
{"learn":[0.1930047607],"iteration":137,"passed_time":0.6614551716,"remaining_time":4.131698246},
{"learn":[0.1927277389],"iteration":138,"passed_time":0.6663546492,"remaining_time":4.127563691},
{"learn":[0.1925251507],"iteration":139,"passed_time":0.6711984415,"remaining_time":4.123076141},
{"learn":[0.1923470109],"iteration":140,"passed_time":0.675970275,"remaining_time":4.11814515},
{"learn":[0.1921872312],"iteration":141,"passed_time":0.6809214548,"remaining_time":4.114300058},
{"learn":[0.1919465042],"iteration":142,"passed_time":0.6856019073,"remaining_time":4.108817025},
{"learn":[0.1916423338],"iteration":143,"passed_time":0.6906363347,"remaining_time":4.105449323},
{"learn":[0.1914036105],"iteration":144,"passed_time":0.6954846996,"remaining_time":4.100961504},
{"learn":[0.1912503145],"iteration":145,"passed_time":0.7007227966,"remaining_time":4.098748413},
{"learn":[0.1911334955],"iteration":146,"passed_time":0.7057083603,"remaining_time":4.095028785},
{"learn":[0.1908103319],"iteration":147,"passed_time":0.7109649541,"remaining_time":4.092852303},
{"learn":[0.1905722148],"iteration":148,"passed_time":0.7161343404,"remaining_time":4.090136401},
{"learn":[0.1903225687],"iteration":149,"passed_time":0.7214200406,"remaining_time":4.088046897},
{"learn":[0.1901479954],"iteration":150,"passed_time":0.7260767417,"remaining_time":4.082378501},
{"learn":[0.1898855804],"iteration":151,"passed_time":0.7313748691,"remaining_time":4.080301901},
{"learn":[0.1897080014],"iteration":152,"passed_time":0.7361348016,"remaining_time":4.075203771},
{"learn":[0.1895101693],"iteration":153,"passed_time":0.7408461165,"remaining_time":4.069842951},
{"learn":[0.1893131336],"iteration":154,"passed_time":0.7459206351,"remaining_time":4.066470559},
{"learn":[0.1891373428],"iteration":155,"passed_time":0.7508536702,"remaining_time":4.062310882},
{"learn":[0.188999755],"iteration":156,"passed_time":0.7557940156,"remaining_time":4.058180606},
{"learn":[0.1888914636],"iteration":157,"passed_time":0.7610631419,"remaining_time":4.055792187},
{"learn":[0.1887208822],"iteration":158,"passed_time":0.7657187564,"remaining_time":4.050122479},
{"learn":[0.1885631663],"iteration":159,"passed_time":0.7707520687,"remaining_time":4.046448361},
{"learn":[0.1883100214],"iteration":160,"passed_time":0.7760780749,"remaining_time":4.044282639},
{"learn":[0.1880064526],"iteration":161,"passed_time":0.7816201198,"remaining_time":4.043195434},
{"learn":[0.1878582253],"iteration":162,"passed_time":0.7871190833,"remaining_time":4.041832348},
{"learn":[0.1877184267],"iteration":163,"passed_time":0.7924826023,"remaining_time":4.039728387},
{"learn":[0.187595941],"iteration":164,"passed_time":0.7975912206,"remaining_time":4.036294965},
{"learn":[0.1873282323],"iteration":165,"passed_time":0.803096232,"remaining_time":4.034832876},
{"learn":[0.1870676956],"iteration":166,"passed_time":0.8088589785,"remaining_time":4.034607959},
{"learn":[0.1868854825],"iteration":167,"passed_time":0.8140545026,"remaining_time":4.031508013},
{"learn":[0.1866865607],"iteration":168,"passed_time":0.8206364823,"remaining_time":4.035200691},
{"learn":[0.1865356428],"iteration":169,"passed_time":0.8260971364,"remaining_time":4.033297783},
{"learn":[0.1864622056],"iteration":170,"passed_time":0.8316779241,"remaining_time":4.031935667},
{"learn":[0.1863304207],"iteration":171,"passed_time":0.8368324328,"remaining_time":4.028472409},
{"learn":[0.1861506206],"iteration":172,"passed_time":0.8415501588,"remaining_time":4.022901626},
{"learn":[0.1860930435],"iteration":173,"passed_time":0.8467535376,"remaining_time":4.019646104},
{"learn":[0.1858858088],"iteration":174,"passed_time":0.8517805232,"remaining_time":4.015536752},
{"learn":[0.1857380656],"iteration":175,"passed_time":0.8570181097,"remaining_time":4.012402968},
{"learn":[0.1855687493],"iteration":176,"passed_time":0.8621093367,"remaining_time":4.008564882},
{"learn":[0.1853884684],"iteration":177,"passed_time":0.8672454728,"remaining_time":4.004920105},
{"learn":[0.1852388598],"iteration":178,"passed_time":0.8730422246,"remaining_time":4.004288639},
{"learn":[0.1851105192],"iteration":179,"passed_time":0.8778102878,"remaining_time":3.998913533},
{"learn":[0.1849447452],"iteration":180,"passed_time":0.8827886273,"remaining_time":3.994496606},
{"learn":[0.18475869],"iteration":181,"passed_time":0.8884402148,"remaining_time":3.993099427},
{"learn":[0.1846482653],"iteration":182,"passed_time":0.8931813194,"remaining_time":3.987590918},
{"learn":[0.1845163459],"iteration":183,"passed_time":0.8984615801,"remaining_time":3.98448179},
{"learn":[0.1843377539],"iteration":184,"passed_time":0.9033982378,"remaining_time":3.97983548},
{"learn":[0.184164593],"iteration":185,"passed_time":0.9085465996,"remaining_time":3.976112538},
{"learn":[0.1839722038],"iteration":186,"passed_time":0.91365193,"remaining_time":3.972187268},
{"learn":[0.183761121],"iteration":187,"passed_time":0.919081744,"remaining_time":3.969650937},
{"learn":[0.1836697896],"iteration":188,"passed_time":0.9237338547,"remaining_time":3.963746858},
{"learn":[0.1834794357],"iteration":189,"passed_time":0.9287609684,"remaining_time":3.959454655},
{"learn":[0.1834176902],"iteration":190,"passed_time":0.9336174417,"remaining_time":3.954431991},
{"learn":[0.183329801],"iteration":191,"passed_time":0.938314293,"remaining_time":3.948739316},
{"learn":[0.1831397825],"iteration":192,"passed_time":0.9431787281,"remaining_time":3.943757687},
{"learn":[0.1830059188],"iteration":193,"passed_time":0.948040352,"remaining_time":3.938765586},
{"learn":[0.1827877984],"iteration":194,"passed_time":0.9531371904,"remaining_time":3.934745837},
{"learn":[0.1826436831],"iteration":195,"passed_time":0.9580286791,"remaining_time":3.929872745},
{"learn":[0.1824892402],"iteration":196,"passed_time":0.9628244074,"remaining_time":3.924609133},
{"learn":[0.1822600404],"iteration":197,"passed_time":0.9675732525,"remaining_time":3.919160346},
{"learn":[0.1820632042],"iteration":198,"passed_time":0.9725157954,"remaining_time":3.914498252},
{"learn":[0.1819162287],"iteration":199,"passed_time":0.9771896706,"remaining_time":3.908758682},
{"learn":[0.1817012509],"iteration":200,"passed_time":0.9820792395,"remaining_time":3.903887126},
{"learn":[0.1816281794],"iteration":201,"passed_time":0.9872458998,"remaining_time":3.90011004},
{"learn":[0.1814298945],"iteration":202,"passed_time":0.9921843432,"remaining_time":3.895423259},
{"learn":[0.1812697487],"iteration":203,"passed_time":0.9969835036,"remaining_time":3.890190534},
{"learn":[0.1811188347],"iteration":204,"passed_time":1.001905223,"remaining_time":3.885437328},
{"learn":[0.1809822052],"iteration":205,"passed_time":1.006532687,"remaining_time":3.879548319},
{"learn":[0.1808736753],"iteration":206,"passed_time":1.011239055,"remaining_time":3.873973771},
{"learn":[0.1807389443],"iteration":207,"passed_time":1.016187829,"remaining_time":3.86933058},
{"learn":[0.1806193768],"iteration":208,"passed_time":1.021135696,"remaining_time":3.86468103},
{"learn":[0.1804530277],"iteration":209,"passed_time":1.02619058,"remaining_time":3.86043123},
{"learn":[0.1803314198],"iteration":210,"passed_time":1.031320611,"remaining_time":3.856454797},
{"learn":[0.1802198037],"iteration":211,"passed_time":1.03601769,"remaining_time":3.850858206},
{"learn":[0.1800637277],"iteration":212,"passed_time":1.040868732,"remaining_time":3.845838931},
{"learn":[0.1798758487],"iteration":213,"passed_time":1.045598649,"remaining_time":3.840376346},
{"learn":[0.1796713552],"iteration":214,"passed_time":1.050514759,"remaining_time":3.835600399},
{"learn":[0.1795639501],"iteration":215,"passed_time":1.055272256,"remaining_time":3.830247446},
{"learn":[0.1793984249],"iteration":216,"passed_time":1.060021603,"remaining_time":3.824870577},
{"learn":[0.1793048419],"iteration":217,"passed_time":1.064732719,"remaining_time":3.819362324},
{"learn":[0.1790932118],"iteration":218,"passed_time":1.06936847,"remaining_time":3.813592579},
{"learn":[0.1790184707],"iteration":219,"passed_time":1.074272652,"remaining_time":3.808784857},
{"learn":[0.1789749699],"iteration":220,"passed_time":1.079037551,"remaining_time":3.803485305},
{"learn":[0.1788861149],"iteration":221,"passed_time":1.083725677,"remaining_time":3.797921517},
{"learn":[0.178765451],"iteration":222,"passed_time":1.088668953,"remaining_time":3.793254604},
{"learn":[0.1785876418],"iteration":223,"passed_time":1.0936981,"remaining_time":3.788882703},
{"learn":[0.17844712],"iteration":224,"passed_time":1.098434489,"remaining_time":3.783496573},
{"learn":[0.17835675],"iteration":225,"passed_time":1.103628192,"remaining_time":3.779682392},
{"learn":[0.1782928962],"iteration":226,"passed_time":1.1085192,"remaining_time":3.774825295},
{"learn":[0.1781840355],"iteration":227,"passed_time":1.113358189,"remaining_time":3.769791762},
{"learn":[0.1780494664],"iteration":228,"passed_time":1.118386468,"remaining_time":3.765397233},
{"learn":[0.1778685516],"iteration":229,"passed_time":1.12331159,"remaining_time":3.760651844},
{"learn":[0.1778165225],"iteration":230,"passed_time":1.128045299,"remaining_time":3.755267683},
{"learn":[0.1776391278],"iteration":231,"passed_time":1.132772239,"remaining_time":3.749866724},
{"learn":[0.1775074639],"iteration":232,"passed_time":1.137565502,"remaining_time":3.744689873},
{"learn":[0.1774006988],"iteration":233,"passed_time":1.142285786,"remaining_time":3.739277402},
{"learn":[0.1772820915],"iteration":234,"passed_time":1.146933263,"remaining_time":3.733633814},
{"learn":[0.1771651327],"iteration":235,"passed_time":1.151756359,"remaining_time":3.728567197},
{"learn":[0.1770250494],"iteration":236,"passed_time":1.156557663,"remaining_time":3.723432476},
{"learn":[0.1768544265],"iteration":237,"passed_time":1.161331383,"remaining_time":3.718212244},
{"learn":[0.1767294544],"iteration":238,"passed_time":1.166212175,"remaining_time":3.713336675},
{"learn":[0.1765450954],"iteration":239,"passed_time":1.171194005,"remaining_time":3.708781017},
{"learn":[0.1764164416],"iteration":240,"passed_time":1.175899437,"remaining_time":3.703351339},
{"learn":[0.176331381],"iteration":241,"passed_time":1.180902953,"remaining_time":3.698861315},
{"learn":[0.1761973432],"iteration":242,"passed_time":1.185696166,"remaining_time":3.693711924},
{"learn":[0.175949235],"iteration":243,"passed_time":1.190573925,"remaining_time":3.688827406},
{"learn":[0.1756946083],"iteration":244,"passed_time":1.195380712,"remaining_time":3.683724236},
{"learn":[0.1755951323],"iteration":245,"passed_time":1.200326047,"remaining_time":3.679048129},
{"learn":[0.1754425082],"iteration":246,"passed_time":1.205280297,"remaining_time":3.674397019},
{"learn":[0.1753995313],"iteration":247,"passed_time":1.210271184,"remaining_time":3.669854557},
{"learn":[0.1752846435],"iteration":248,"passed_time":1.21503378,"remaining_time":3.664619956},
{"learn":[0.1750861574],"iteration":249,"passed_time":1.21986035,"remaining_time":3.65958105},
{"learn":[0.1749511842],"iteration":250,"passed_time":1.224502674,"remaining_time":3.653994035},
{"learn":[0.1748132637],"iteration":251,"passed_time":1.228908123,"remaining_time":3.647711414},
{"learn":[0.1747331983],"iteration":252,"passed_time":1.234040825,"remaining_time":3.643590894},
{"learn":[0.1745690856],"iteration":253,"passed_time":1.238964578,"remaining_time":3.638848721},
{"learn":[0.1744425283],"iteration":254,"passed_time":1.243643335,"remaining_time":3.633389351},
{"learn":[0.1743801688],"iteration":255,"passed_time":1.248317434,"remaining_time":3.627922543},
{"learn":[0.1742151714],"iteration":256,"passed_time":1.253077662,"remaining_time":3.622710906},
{"learn":[0.1740889396],"iteration":257,"passed_time":1.258327964,"remaining_time":3.618912206},
{"learn":[0.1740432439],"iteration":258,"passed_time":1.263159818,"remaining_time":3.613905115},
{"learn":[0.173933706],"iteration":259,"passed_time":1.268209713,"remaining_time":3.609519953},
{"learn":[0.1738224723],"iteration":260,"passed_time":1.273253929,"remaining_time":3.605113615},
{"learn":[0.1737438058],"iteration":261,"passed_time":1.278141889,"remaining_time":3.600262269},
{"learn":[0.1736818621],"iteration":262,"passed_time":1.283294986,"remaining_time":3.596153629},
{"learn":[0.1735548261],"iteration":263,"passed_time":1.288283278,"remaining_time":3.591577624},
{"learn":[0.1734480437],"iteration":264,"passed_time":1.293188047,"remaining_time":3.586766847},
{"learn":[0.1733318577],"iteration":265,"passed_time":1.298138321,"remaining_time":3.582080932},
{"learn":[0.173161245],"iteration":266,"passed_time":1.303153378,"remaining_time":3.577570886},
{"learn":[0.1730316029],"iteration":267,"passed_time":1.308711902,"remaining_time":3.574541463},
{"learn":[0.1729267924],"iteration":268,"passed_time":1.313762786,"remaining_time":3.570113742},
{"learn":[0.1727696618],"iteration":269,"passed_time":1.318714776,"remaining_time":3.565414023},
{"learn":[0.1726701705],"iteration":270,"passed_time":1.32396023,"remaining_time":3.561501872},
{"learn":[0.1725980191],"iteration":271,"passed_time":1.329059088,"remaining_time":3.557187559},
{"learn":[0.172484641],"iteration":272,"passed_time":1.334070651,"remaining_time":3.552635029},
{"learn":[0.1723868246],"iteration":273,"passed_time":1.338983806,"remaining_time":3.547818405},
{"learn":[0.1722610843],"iteration":274,"passed_time":1.344060313,"remaining_time":3.543431734},
{"learn":[0.1722479507],"iteration":275,"passed_time":1.349065192,"remaining_time":3.538852172},
{"learn":[0.1720995283],"iteration":276,"passed_time":1.35409606,"remaining_time":3.534337369},
{"learn":[0.1719961032],"iteration":277,"passed_time":1.359046371,"remaining_time":3.529609639},
{"learn":[0.1719263252],"iteration":278,"passed_time":1.36452222,"remaining_time":3.526238424},
{"learn":[0.1718139834],"iteration":279,"passed_time":1.369416646,"remaining_time":3.52135709},
{"learn":[0.1716968469],"iteration":280,"passed_time":1.374406458,"remaining_time":3.516719726},
{"learn":[0.1715705701],"iteration":281,"passed_time":1.379273326,"remaining_time":3.511766838},
{"learn":[0.1715255502],"iteration":282,"passed_time":1.384173117,"remaining_time":3.506897969},
{"learn":[0.1713833844],"iteration":283,"passed_time":1.389162492,"remaining_time":3.502254733},
{"learn":[0.1712714379],"iteration":284,"passed_time":1.394064467,"remaining_time":3.497389803},
{"learn":[0.1711125094],"iteration":285,"passed_time":1.399124378,"remaining_time":3.492918903},
{"learn":[0.1710369609],"iteration":286,"passed_time":1.404095644,"remaining_time":3.488223674},
{"learn":[0.1709340577],"iteration":287,"passed_time":1.409318419,"remaining_time":3.484148314},
{"learn":[0.1708220139],"iteration":288,"passed_time":1.414220789,"remaining_time":3.479276752},
{"learn":[0.170682743],"iteration":289,"passed_time":1.419094945,"remaining_time":3.474335899},
{"learn":[0.1705966413],"iteration":290,"passed_time":1.424196362,"remaining_time":3.469949212},
{"learn":[0.1704788243],"iteration":291,"passed_time":1.429451545,"remaining_time":3.465930458},
{"learn":[0.1703532116],"iteration":292,"passed_time":1.434240291,"remaining_time":3.460777766},
{"learn":[0.1702057909],"iteration":293,"passed_time":1.439093997,"remaining_time":3.455783545},
{"learn":[0.1700885027],"iteration":294,"passed_time":1.443978647,"remaining_time":3.450864224},
{"learn":[0.1700320685],"iteration":295,"passed_time":1.449002269,"remaining_time":3.446275667},
{"learn":[0.169962143],"iteration":296,"passed_time":1.454130802,"remaining_time":3.441932503},
{"learn":[0.1698645131],"iteration":297,"passed_time":1.459165855,"remaining_time":3.437363859},
{"learn":[0.1697899066],"iteration":298,"passed_time":1.464255396,"remaining_time":3.432919841},
{"learn":[0.1696475845],"iteration":299,"passed_time":1.469285137,"remaining_time":3.428331986},
{"learn":[0.1694415026],"iteration":300,"passed_time":1.474511409,"remaining_time":3.42419759},
{"learn":[0.1693683466],"iteration":301,"passed_time":1.479189549,"remaining_time":3.41878909},
{"learn":[0.1692436021],"iteration":302,"passed_time":1.484173636,"remaining_time":3.414089188},
{"learn":[0.1691624645],"iteration":303,"passed_time":1.489175077,"remaining_time":3.409427149},
{"learn":[0.1691123932],"iteration":304,"passed_time":1.493952883,"remaining_time":3.40425329},
{"learn":[0.1690353282],"iteration":305,"passed_time":1.498867068,"remaining_time":3.399391324},
{"learn":[0.1688716149],"iteration":306,"passed_time":1.503804966,"remaining_time":3.394582545},
{"learn":[0.1687805469],"iteration":307,"passed_time":1.508864939,"remaining_time":3.3900472},
{"learn":[0.1687005954],"iteration":308,"passed_time":1.514108591,"remaining_time":3.385919212},
{"learn":[0.1685710032],"iteration":309,"passed_time":1.519209589,"remaining_time":3.381466505},
{"learn":[0.1684830698],"iteration":310,"passed_time":1.524058981,"remaining_time":3.376452213},
{"learn":[0.1684473807],"iteration":311,"passed_time":1.52901223,"remaining_time":3.371667993},
{"learn":[0.1683798937],"iteration":312,"passed_time":1.534089431,"remaining_time":3.367154758},
{"learn":[0.168241591],"iteration":313,"passed_time":1.539373221,"remaining_time":3.363089266},
{"learn":[0.1682252385],"iteration":314,"passed_time":1.54427774,"remaining_time":3.358191275},
{"learn":[0.1680734112],"iteration":315,"passed_time":1.549138439,"remaining_time":3.353198392},
{"learn":[0.1678572759],"iteration":316,"passed_time":1.554005507,"remaining_time":3.348220068},
{"learn":[0.1677533139],"iteration":317,"passed_time":1.559049987,"remaining_time":3.343622928},
{"learn":[0.1676467747],"iteration":318,"passed_time":1.564001795,"remaining_time":3.338825148},
{"learn":[0.167537544],"iteration":319,"passed_time":1.568912769,"remaining_time":3.333939635},
{"learn":[0.1674735334],"iteration":320,"passed_time":1.573868485,"remaining_time":3.329148603},
{"learn":[0.1673833417],"iteration":321,"passed_time":1.579167894,"remaining_time":3.325080224},
{"learn":[0.1672797619],"iteration":322,"passed_time":1.584252764,"remaining_time":3.320554554},
{"learn":[0.1672292297],"iteration":323,"passed_time":1.589217119,"remaining_time":3.31577399},
{"learn":[0.1671528198],"iteration":324,"passed_time":1.594548793,"remaining_time":3.311755186},
{"learn":[0.1670130833],"iteration":325,"passed_time":1.599451506,"remaining_time":3.306841457},
{"learn":[0.1669140388],"iteration":326,"passed_time":1.604556239,"remaining_time":3.302343575},
{"learn":[0.1668322416],"iteration":327,"passed_time":1.609490367,"remaining_time":3.297492459},
{"learn":[0.166791953],"iteration":328,"passed_time":1.614243596,"remaining_time":3.292271893},
{"learn":[0.1667507044],"iteration":329,"passed_time":1.619377946,"remaining_time":3.287827951},
{"learn":[0.1666265721],"iteration":330,"passed_time":1.624858925,"remaining_time":3.284080424},
{"learn":[0.1664450938],"iteration":331,"passed_time":1.630138879,"remaining_time":3.279917985},
{"learn":[0.1662634879],"iteration":332,"passed_time":1.635336341,"remaining_time":3.275583602},
{"learn":[0.1662003683],"iteration":333,"passed_time":1.640656205,"remaining_time":3.271488122},
{"learn":[0.1660932363],"iteration":334,"passed_time":1.645854373,"remaining_time":3.267143756},
{"learn":[0.1659277331],"iteration":335,"passed_time":1.651170396,"remaining_time":3.263027211},
{"learn":[0.1658126517],"iteration":336,"passed_time":1.656264003,"remaining_time":3.258465976},
{"learn":[0.1656702482],"iteration":337,"passed_time":1.66136965,"remaining_time":3.253925172},
{"learn":[0.1655066513],"iteration":338,"passed_time":1.666696568,"remaining_time":3.249812482},
{"learn":[0.1654058772],"iteration":339,"passed_time":1.671512091,"remaining_time":3.244699941},
{"learn":[0.1652713062],"iteration":340,"passed_time":1.676473602,"remaining_time":3.239871272},
{"learn":[0.1652008666],"iteration":341,"passed_time":1.681629708,"remaining_time":3.235416223},
{"learn":[0.1651375714],"iteration":342,"passed_time":1.686676438,"remaining_time":3.230747579},
{"learn":[0.1650768597],"iteration":343,"passed_time":1.691675385,"remaining_time":3.225985617},
{"learn":[0.1650337186],"iteration":344,"passed_time":1.696595836,"remaining_time":3.221073253},
{"learn":[0.1649911219],"iteration":345,"passed_time":1.701652078,"remaining_time":3.216417511},
{"learn":[0.16490962],"iteration":346,"passed_time":1.707065009,"remaining_time":3.212430693},
{"learn":[0.1647720135],"iteration":347,"passed_time":1.712195724,"remaining_time":3.207906931},
{"learn":[0.1646064536],"iteration":348,"passed_time":1.717548237,"remaining_time":3.203793416},
{"learn":[0.1645349732],"iteration":349,"passed_time":1.722905339,"remaining_time":3.199681343},
{"learn":[0.1644288275],"iteration":350,"passed_time":1.727762837,"remaining_time":3.194638409},
{"learn":[0.1643669302],"iteration":351,"passed_time":1.734152469,"remaining_time":3.192417045},
{"learn":[0.1643041465],"iteration":352,"passed_time":1.739759159,"remaining_time":3.188737041},
{"learn":[0.164182934],"iteration":353,"passed_time":1.745414658,"remaining_time":3.185135224},
{"learn":[0.1640366859],"iteration":354,"passed_time":1.750638194,"remaining_time":3.180737001},
{"learn":[0.1639847036],"iteration":355,"passed_time":1.756853819,"remaining_time":3.178128818},
{"learn":[0.1638124337],"iteration":356,"passed_time":1.762665521,"remaining_time":3.174772913},
{"learn":[0.1637039357],"iteration":357,"passed_time":1.768136771,"remaining_time":3.170792757},
{"learn":[0.1636662142],"iteration":358,"passed_time":1.773656008,"remaining_time":3.166889976},
{"learn":[0.1635900404],"iteration":359,"passed_time":1.779055109,"remaining_time":3.162764639},
{"learn":[0.1635187144],"iteration":360,"passed_time":1.785837312,"remaining_time":3.16108045},
{"learn":[0.1633961167],"iteration":361,"passed_time":1.790817562,"remaining_time":3.156192277},
{"learn":[0.1632230698],"iteration":362,"passed_time":1.799083996,"remaining_time":3.157070263},
{"learn":[0.1631663409],"iteration":363,"passed_time":1.808306329,"remaining_time":3.159568201},
{"learn":[0.1630307313],"iteration":364,"passed_time":1.814933207,"remaining_time":3.157486539},
{"learn":[0.1629709136],"iteration":365,"passed_time":1.820306265,"remaining_time":3.153208121},
{"learn":[0.1628332102],"iteration":366,"passed_time":1.826676081,"remaining_time":3.150642941},
{"learn":[0.16276948],"iteration":367,"passed_time":1.832121386,"remaining_time":3.146469337},
{"learn":[0.1625785731],"iteration":368,"passed_time":1.837471478,"remaining_time":3.142126023},
{"learn":[0.1624614174],"iteration":369,"passed_time":1.843733855,"remaining_time":3.139330618},
{"learn":[0.1624028662],"iteration":370,"passed_time":1.849350672,"remaining_time":3.135422028},
{"learn":[0.1622774466],"iteration":371,"passed_time":1.855412792,"remaining_time":3.132256004},
{"learn":[0.1621548996],"iteration":372,"passed_time":1.860985177,"remaining_time":3.128251222},
{"learn":[0.1620875805],"iteration":373,"passed_time":1.866174187,"remaining_time":3.123596366},
{"learn":[0.1619964478],"iteration":374,"passed_time":1.87149947,"remaining_time":3.119165784},
{"learn":[0.1618861995],"iteration":375,"passed_time":1.876743889,"remaining_time":3.114596242},
{"learn":[0.1617912578],"iteration":376,"passed_time":1.881822385,"remaining_time":3.109748928},
{"learn":[0.1617147701],"iteration":377,"passed_time":1.88671821,"remaining_time":3.104599806},
{"learn":[0.1616264574],"iteration":378,"passed_time":1.891720905,"remaining_time":3.099627129},
{"learn":[0.1615140682],"iteration":379,"passed_time":1.896983819,"remaining_time":3.095078862},
{"learn":[0.1613637914],"iteration":380,"passed_time":1.902159241,"remaining_time":3.090384699},
{"learn":[0.1611930304],"iteration":381,"passed_time":1.907389377,"remaining_time":3.085776532},
{"learn":[0.1611265055],"iteration":382,"passed_time":1.912325778,"remaining_time":3.080691918},
{"learn":[0.1610303436],"iteration":383,"passed_time":1.917283072,"remaining_time":3.075641595},
{"learn":[0.1609128901],"iteration":384,"passed_time":1.922339061,"remaining_time":3.070749409},
{"learn":[0.1607689692],"iteration":385,"passed_time":1.927736019,"remaining_time":3.066398746},
{"learn":[0.1607086102],"iteration":386,"passed_time":1.932513291,"remaining_time":3.061061104},
{"learn":[0.1605630563],"iteration":387,"passed_time":1.937719424,"remaining_time":3.056402803},
{"learn":[0.1604094474],"iteration":388,"passed_time":1.942736476,"remaining_time":3.051444696},
{"learn":[0.1602774485],"iteration":389,"passed_time":1.948016374,"remaining_time":3.046897405},
{"learn":[0.1602053805],"iteration":390,"passed_time":1.95312254,"remaining_time":3.042075772},
{"learn":[0.160117614],"iteration":391,"passed_time":1.957991848,"remaining_time":3.036885315},
{"learn":[0.1600344314],"iteration":392,"passed_time":1.962761633,"remaining_time":3.031542777},
{"learn":[0.1599244117],"iteration":393,"passed_time":1.967723374,"remaining_time":3.026498387},
{"learn":[0.159808509],"iteration":394,"passed_time":1.972716899,"remaining_time":3.021503099},
{"learn":[0.1596749785],"iteration":395,"passed_time":1.977988224,"remaining_time":3.016931533},
{"learn":[0.1595950108],"iteration":396,"passed_time":1.982974868,"remaining_time":3.011924045},
{"learn":[0.1595320129],"iteration":397,"passed_time":1.988127044,"remaining_time":3.007167036},
{"learn":[0.1594653021],"iteration":398,"passed_time":1.993287873,"remaining_time":3.002421082},
{"learn":[0.1593824164],"iteration":399,"passed_time":1.998588106,"remaining_time":2.997882159},
{"learn":[0.1592753545],"iteration":400,"passed_time":2.003676764,"remaining_time":2.993023395},
{"learn":[0.1591793577],"iteration":401,"passed_time":2.008919098,"remaining_time":2.988392092},
{"learn":[0.1590639667],"iteration":402,"passed_time":2.014119241,"remaining_time":2.983695253},
{"learn":[0.1589594929],"iteration":403,"passed_time":2.019246967,"remaining_time":2.97888909},
{"learn":[0.1588415294],"iteration":404,"passed_time":2.024220614,"remaining_time":2.973854976},
{"learn":[0.1587615296],"iteration":405,"passed_time":2.029322703,"remaining_time":2.969009077},
{"learn":[0.1586847762],"iteration":406,"passed_time":2.034245936,"remaining_time":2.963901327},
{"learn":[0.158586866],"iteration":407,"passed_time":2.039298099,"remaining_time":2.958981556},
{"learn":[0.158459104],"iteration":408,"passed_time":2.044492139,"remaining_time":2.954266147},
{"learn":[0.1583828144],"iteration":409,"passed_time":2.049534136,"remaining_time":2.94932961},
{"learn":[0.1583229499],"iteration":410,"passed_time":2.054656163,"remaining_time":2.94450725},
{"learn":[0.1582124733],"iteration":411,"passed_time":2.059731216,"remaining_time":2.939616396},
{"learn":[0.1580899585],"iteration":412,"passed_time":2.064738206,"remaining_time":2.93462791},
{"learn":[0.1579888168],"iteration":413,"passed_time":2.069677634,"remaining_time":2.929543704},
{"learn":[0.1579137962],"iteration":414,"passed_time":2.074968713,"remaining_time":2.924955897},
{"learn":[0.1577714421],"iteration":415,"passed_time":2.080084388,"remaining_time":2.920118467},
{"learn":[0.1576895454],"iteration":416,"passed_time":2.08499874,"remaining_time":2.914998238},
{"learn":[0.1575154939],"iteration":417,"passed_time":2.090072282,"remaining_time":2.910100641},
{"learn":[0.1573768331],"iteration":418,"passed_time":2.095067846,"remaining_time":2.905094078},
{"learn":[0.1573107673],"iteration":419,"passed_time":2.1001504,"remaining_time":2.900207695},
{"learn":[0.1571806818],"iteration":420,"passed_time":2.105087922,"remaining_time":2.895120919},
{"learn":[0.1570895965],"iteration":421,"passed_time":2.110047937,"remaining_time":2.890065658},
{"learn":[0.1569283239],"iteration":422,"passed_time":2.115271641,"remaining_time":2.885370536},
{"learn":[0.1568634134],"iteration":423,"passed_time":2.120591126,"remaining_time":2.880803039},
{"learn":[0.1567607373],"iteration":424,"passed_time":2.125863916,"remaining_time":2.876168828},
{"learn":[0.1565649844],"iteration":425,"passed_time":2.13124312,"remaining_time":2.871675002},
{"learn":[0.1564864524],"iteration":426,"passed_time":2.13630079,"remaining_time":2.866745556},
{"learn":[0.1563350444],"iteration":427,"passed_time":2.141144558,"remaining_time":2.861529644},
{"learn":[0.1561906948],"iteration":428,"passed_time":2.146246021,"remaining_time":2.856658457},
{"learn":[0.1560525776],"iteration":429,"passed_time":2.151934721,"remaining_time":2.85256463},
{"learn":[0.1560262077],"iteration":430,"passed_time":2.157177812,"remaining_time":2.847875116},
{"learn":[0.1559166385],"iteration":431,"passed_time":2.162222269,"remaining_time":2.842921872},
{"learn":[0.1558053689],"iteration":432,"passed_time":2.167227268,"remaining_time":2.837916539},
{"learn":[0.1557360552],"iteration":433,"passed_time":2.172072115,"remaining_time":2.832702344},
{"learn":[0.1556217686],"iteration":434,"passed_time":2.177177049,"remaining_time":2.827827662},
{"learn":[0.1555383878],"iteration":435,"passed_time":2.182361554,"remaining_time":2.823054854},
{"learn":[0.1554298248],"iteration":436,"passed_time":2.18733755,"remaining_time":2.818011535},
{"learn":[0.1553762114],"iteration":437,"passed_time":2.192348962,"remaining_time":2.813013965},
{"learn":[0.1552567012],"iteration":438,"passed_time":2.197384662,"remaining_time":2.80804737},
{"learn":[0.1551332126],"iteration":439,"passed_time":2.202474171,"remaining_time":2.803148945},
{"learn":[0.1550551246],"iteration":440,"passed_time":2.207365948,"remaining_time":2.797999013},
{"learn":[0.1549565549],"iteration":441,"passed_time":2.212289856,"remaining_time":2.792890814},
{"learn":[0.1548134919],"iteration":442,"passed_time":2.217364627,"remaining_time":2.787973132},
{"learn":[0.1547040047],"iteration":443,"passed_time":2.222482619,"remaining_time":2.783108866},
{"learn":[0.1546071337],"iteration":444,"passed_time":2.227474375,"remaining_time":2.778086018},
{"learn":[0.1545648495],"iteration":445,"passed_time":2.23264739,"remaining_time":2.773288462},
{"learn":[0.1544431596],"iteration":446,"passed_time":2.237553634,"remaining_time":2.768159193},
{"learn":[0.1543908653],"iteration":447,"passed_time":2.242471736,"remaining_time":2.763045532},
{"learn":[0.1543370864],"iteration":448,"passed_time":2.247363623,"remaining_time":2.75790057},
{"learn":[0.1542412486],"iteration":449,"passed_time":2.252370594,"remaining_time":2.752897392},
{"learn":[0.1541030824],"iteration":450,"passed_time":2.25722809,"remaining_time":2.747712242},
{"learn":[0.154009246],"iteration":451,"passed_time":2.262280036,"remaining_time":2.742764291},
{"learn":[0.1539082191],"iteration":452,"passed_time":2.267291395,"remaining_time":2.737766873},
{"learn":[0.1538644835],"iteration":453,"passed_time":2.2724209,"remaining_time":2.732911479},
{"learn":[0.1537888535],"iteration":454,"passed_time":2.27749795,"remaining_time":2.72799205},
{"learn":[0.1536859966],"iteration":455,"passed_time":2.282614971,"remaining_time":2.723119615},
{"learn":[0.1536226033],"iteration":456,"passed_time":2.2875033,"remaining_time":2.71797438},
{"learn":[0.153530251],"iteration":457,"passed_time":2.292421145,"remaining_time":2.712865198},
{"learn":[0.1534290098],"iteration":458,"passed_time":2.297519884,"remaining_time":2.70797006},
{"learn":[0.1533114878],"iteration":459,"passed_time":2.302437178,"remaining_time":2.702861035},
{"learn":[0.1532013892],"iteration":460,"passed_time":2.30724539,"remaining_time":2.697625304},
{"learn":[0.1530825352],"iteration":461,"passed_time":2.312132572,"remaining_time":2.692483385},
{"learn":[0.152972883],"iteration":462,"passed_time":2.317253025,"remaining_time":2.68761312},
{"learn":[0.1528515384],"iteration":463,"passed_time":2.322057401,"remaining_time":2.682376653},
{"learn":[0.152781444],"iteration":464,"passed_time":2.327042224,"remaining_time":2.677349656},
{"learn":[0.152674991],"iteration":465,"passed_time":2.332060414,"remaining_time":2.672361075},
{"learn":[0.1526295582],"iteration":466,"passed_time":2.337055349,"remaining_time":2.667345827},
{"learn":[0.1525821786],"iteration":467,"passed_time":2.341898931,"remaining_time":2.662158614},
{"learn":[0.1525387073],"iteration":468,"passed_time":2.346761373,"remaining_time":2.65699422},
{"learn":[0.1524850273],"iteration":469,"passed_time":2.351546591,"remaining_time":2.651744029},
{"learn":[0.1523238068],"iteration":470,"passed_time":2.356424871,"remaining_time":2.646600333},
{"learn":[0.15230278],"iteration":471,"passed_time":2.361303801,"remaining_time":2.641458489},
{"learn":[0.152192504],"iteration":472,"passed_time":2.3663624,"remaining_time":2.636517938},
{"learn":[0.1521051656],"iteration":473,"passed_time":2.371196991,"remaining_time":2.631328306},
{"learn":[0.1520222902],"iteration":474,"passed_time":2.376282872,"remaining_time":2.626417911},
{"learn":[0.1519008282],"iteration":475,"passed_time":2.380910913,"remaining_time":2.62100277},
{"learn":[0.1518383911],"iteration":476,"passed_time":2.385839746,"remaining_time":2.615920728},
{"learn":[0.1517040841],"iteration":477,"passed_time":2.390651111,"remaining_time":2.610711046},
{"learn":[0.1515759118],"iteration":478,"passed_time":2.3954997,"remaining_time":2.605543515},
{"learn":[0.1514519231],"iteration":479,"passed_time":2.40032687,"remaining_time":2.600354109},
{"learn":[0.1513761774],"iteration":480,"passed_time":2.405266901,"remaining_time":2.595287986},
{"learn":[0.1512129486],"iteration":481,"passed_time":2.410386205,"remaining_time":2.590415051},
{"learn":[0.1511025532],"iteration":482,"passed_time":2.415586861,"remaining_time":2.585628172},
{"learn":[0.1510653484],"iteration":483,"passed_time":2.420783477,"remaining_time":2.580835277},
{"learn":[0.1509886582],"iteration":484,"passed_time":2.425813672,"remaining_time":2.575864002},
{"learn":[0.1509094826],"iteration":485,"passed_time":2.430608294,"remaining_time":2.57064334},
{"learn":[0.1508722447],"iteration":486,"passed_time":2.435651922,"remaining_time":2.565686727},
{"learn":[0.1507677372],"iteration":487,"passed_time":2.440928788,"remaining_time":2.560974466},
{"learn":[0.1506355421],"iteration":488,"passed_time":2.44624595,"remaining_time":2.556302005},
{"learn":[0.150541225],"iteration":489,"passed_time":2.451323445,"remaining_time":2.551377464},
{"learn":[0.150378437],"iteration":490,"passed_time":2.456311588,"remaining_time":2.546359671},
{"learn":[0.1502323576],"iteration":491,"passed_time":2.461340592,"remaining_time":2.541384188},
{"learn":[0.1501856546],"iteration":492,"passed_time":2.466532726,"remaining_time":2.536576252},
{"learn":[0.1501104536],"iteration":493,"passed_time":2.471704003,"remaining_time":2.531745396},
{"learn":[0.1500897734],"iteration":494,"passed_time":2.476778923,"remaining_time":2.526814861},
{"learn":[0.150070363],"iteration":495,"passed_time":2.481936473,"remaining_time":2.521967707},
{"learn":[0.1500350383],"iteration":496,"passed_time":2.487171336,"remaining_time":2.517197549},
{"learn":[0.1498868114],"iteration":497,"passed_time":2.492613082,"remaining_time":2.512634071},
{"learn":[0.1498108852],"iteration":498,"passed_time":2.498178496,"remaining_time":2.508191235},
{"learn":[0.1497874342],"iteration":499,"passed_time":2.503434871,"remaining_time":2.503434871},
{"learn":[0.1497123976],"iteration":500,"passed_time":2.50893165,"remaining_time":2.498915954},
{"learn":[0.1496670294],"iteration":501,"passed_time":2.514335907,"remaining_time":2.494301358},
{"learn":[0.1496100017],"iteration":502,"passed_time":2.519731754,"remaining_time":2.489675312},
{"learn":[0.1495345532],"iteration":503,"passed_time":2.524950458,"remaining_time":2.48487188},
{"learn":[0.149462881],"iteration":504,"passed_time":2.530218647,"remaining_time":2.480115308},
{"learn":[0.1494129284],"iteration":505,"passed_time":2.536124118,"remaining_time":2.475978882},
{"learn":[0.1493287391],"iteration":506,"passed_time":2.541349709,"remaining_time":2.471174372},
{"learn":[0.149184851],"iteration":507,"passed_time":2.546321633,"remaining_time":2.466122526},
{"learn":[0.1491370421],"iteration":508,"passed_time":2.551620016,"remaining_time":2.461385909},
{"learn":[0.1490115749],"iteration":509,"passed_time":2.55701831,"remaining_time":2.456743083},
{"learn":[0.1489185466],"iteration":510,"passed_time":2.562607858,"remaining_time":2.452280318},
{"learn":[0.1488602827],"iteration":511,"passed_time":2.568226779,"remaining_time":2.447841149},
{"learn":[0.1488131333],"iteration":512,"passed_time":2.574266165,"remaining_time":2.443796535},
{"learn":[0.1486704866],"iteration":513,"passed_time":2.579742508,"remaining_time":2.439211788},
{"learn":[0.1485473281],"iteration":514,"passed_time":2.584945531,"remaining_time":2.43436618},
{"learn":[0.1484782247],"iteration":515,"passed_time":2.590715382,"remaining_time":2.430050863},
{"learn":[0.1483507124],"iteration":516,"passed_time":2.595744817,"remaining_time":2.425038195},
{"learn":[0.148212893],"iteration":517,"passed_time":2.600804891,"remaining_time":2.420053972},
{"learn":[0.1481111063],"iteration":518,"passed_time":2.605734539,"remaining_time":2.414948581},
{"learn":[0.1480225301],"iteration":519,"passed_time":2.611031679,"remaining_time":2.410183088},
{"learn":[0.1479271269],"iteration":520,"passed_time":2.616610399,"remaining_time":2.405674436},
{"learn":[0.1478497945],"iteration":521,"passed_time":2.621969392,"remaining_time":2.400960477},
{"learn":[0.1477911505],"iteration":522,"passed_time":2.627880772,"remaining_time":2.396747855},
{"learn":[0.1476907784],"iteration":523,"passed_time":2.633580596,"remaining_time":2.392336572},
{"learn":[0.1476573996],"iteration":524,"passed_time":2.638695951,"remaining_time":2.387391575},
{"learn":[0.1475742144],"iteration":525,"passed_time":2.643905297,"remaining_time":2.382530629},
{"learn":[0.147505774],"iteration":526,"passed_time":2.648933855,"remaining_time":2.377506098},
{"learn":[0.1474027353],"iteration":527,"passed_time":2.653761818,"remaining_time":2.372302231},
{"learn":[0.1473137307],"iteration":528,"passed_time":2.658575027,"remaining_time":2.367086649},
{"learn":[0.1472515372],"iteration":529,"passed_time":2.663533592,"remaining_time":2.362001487},
{"learn":[0.147172807],"iteration":530,"passed_time":2.668760211,"remaining_time":2.357153557},
{"learn":[0.1470945052],"iteration":531,"passed_time":2.673871106,"remaining_time":2.352202402},
{"learn":[0.1470071815],"iteration":532,"passed_time":2.678757476,"remaining_time":2.347053924},
{"learn":[0.1469474949],"iteration":533,"passed_time":2.683744414,"remaining_time":2.341994189},
{"learn":[0.1468831444],"iteration":534,"passed_time":2.68913618,"remaining_time":2.337286586},
{"learn":[0.1467749893],"iteration":535,"passed_time":2.694175905,"remaining_time":2.332271679},
{"learn":[0.146681383],"iteration":536,"passed_time":2.700158055,"remaining_time":2.328069236},
{"learn":[0.1465865854],"iteration":537,"passed_time":2.705173025,"remaining_time":2.323029623},
{"learn":[0.146469974],"iteration":538,"passed_time":2.710044493,"remaining_time":2.317867368},
{"learn":[0.146420186],"iteration":539,"passed_time":2.715096792,"remaining_time":2.31286023},
{"learn":[0.1463296434],"iteration":540,"passed_time":2.720152415,"remaining_time":2.307855746},
{"learn":[0.1462210961],"iteration":541,"passed_time":2.725114131,"remaining_time":2.302771719},
{"learn":[0.1461314485],"iteration":542,"passed_time":2.730106828,"remaining_time":2.297714218},
{"learn":[0.1460275355],"iteration":543,"passed_time":2.735192256,"remaining_time":2.292734685},
{"learn":[0.1459391216],"iteration":544,"passed_time":2.740901463,"remaining_time":2.288275534},
{"learn":[0.145851189],"iteration":545,"passed_time":2.746215464,"remaining_time":2.283483188},
{"learn":[0.1457035239],"iteration":546,"passed_time":2.751387843,"remaining_time":2.278571651},
{"learn":[0.1456239013],"iteration":547,"passed_time":2.756947615,"remaining_time":2.273978689},
{"learn":[0.1455396927],"iteration":548,"passed_time":2.76213987,"remaining_time":2.269080294},
{"learn":[0.1454357555],"iteration":549,"passed_time":2.767200275,"remaining_time":2.264072952},
{"learn":[0.1453512025],"iteration":550,"passed_time":2.772054742,"remaining_time":2.258897603},
{"learn":[0.1452184607],"iteration":551,"passed_time":2.777367251,"remaining_time":2.25409516},
{"learn":[0.1450875346],"iteration":552,"passed_time":2.782143317,"remaining_time":2.248857256},
{"learn":[0.1450047471],"iteration":553,"passed_time":2.787083484,"remaining_time":2.24375313},
{"learn":[0.1449082224],"iteration":554,"passed_time":2.792246145,"remaining_time":2.23882799},
{"learn":[0.144798042],"iteration":555,"passed_time":2.797038292,"remaining_time":2.233606118},
{"learn":[0.1447926824],"iteration":556,"passed_time":2.800966308,"remaining_time":2.227698518},
{"learn":[0.1447219011],"iteration":557,"passed_time":2.805898784,"remaining_time":2.22259366},
{"learn":[0.1446332752],"iteration":558,"passed_time":2.810651544,"remaining_time":2.21734764},
{"learn":[0.14456787],"iteration":559,"passed_time":2.815343246,"remaining_time":2.212055408},
{"learn":[0.144489433],"iteration":560,"passed_time":2.820232196,"remaining_time":2.206919668},
{"learn":[0.1444058537],"iteration":561,"passed_time":2.82500974,"remaining_time":2.201697983},
{"learn":[0.1443445039],"iteration":562,"passed_time":2.830045747,"remaining_time":2.196678493},
{"learn":[0.1442975691],"iteration":563,"passed_time":2.834912757,"remaining_time":2.191528302},
{"learn":[0.1442349347],"iteration":564,"passed_time":2.839700963,"remaining_time":2.18631844},
{"learn":[0.1442241658],"iteration":565,"passed_time":2.844524566,"remaining_time":2.181137211},
{"learn":[0.144108538],"iteration":566,"passed_time":2.849322879,"remaining_time":2.175937931},
{"learn":[0.1440367159],"iteration":567,"passed_time":2.854036311,"remaining_time":2.170675504},
{"learn":[0.1439574237],"iteration":568,"passed_time":2.859098381,"remaining_time":2.16567909},
{"learn":[0.1439158484],"iteration":569,"passed_time":2.863603401,"remaining_time":2.160262215},
{"learn":[0.1438861966],"iteration":570,"passed_time":2.868560956,"remaining_time":2.155188529},
{"learn":[0.1438811009],"iteration":571,"passed_time":2.87280466,"remaining_time":2.149581109},
{"learn":[0.1438444562],"iteration":572,"passed_time":2.877707453,"remaining_time":2.144469603},
{"learn":[0.1438158103],"iteration":573,"passed_time":2.882449951,"remaining_time":2.139239859},
{"learn":[0.1438056352],"iteration":574,"passed_time":2.887127458,"remaining_time":2.133963773},
{"learn":[0.1437700956],"iteration":575,"passed_time":2.89190189,"remaining_time":2.128761113},
{"learn":[0.1436663305],"iteration":576,"passed_time":2.896488701,"remaining_time":2.123422392},
{"learn":[0.143596967],"iteration":577,"passed_time":2.901274248,"remaining_time":2.118231372},
{"learn":[0.1435732498],"iteration":578,"passed_time":2.9059813,"remaining_time":2.112984676},
{"learn":[0.143495591],"iteration":579,"passed_time":2.91058118,"remaining_time":2.107662234},
{"learn":[0.1434056633],"iteration":580,"passed_time":2.915165115,"remaining_time":2.10233078},
{"learn":[0.1433265368],"iteration":581,"passed_time":2.919746803,"remaining_time":2.097000281},
{"learn":[0.1432361306],"iteration":582,"passed_time":2.924464867,"remaining_time":2.091769896},
{"learn":[0.143097305],"iteration":583,"passed_time":2.929402964,"remaining_time":2.086698002},
{"learn":[0.1430913351],"iteration":584,"passed_time":2.934038097,"remaining_time":2.081411641},
{"learn":[0.1430265566],"iteration":585,"passed_time":2.938996578,"remaining_time":2.076355944},
{"learn":[0.1429479239],"iteration":586,"passed_time":2.943518799,"remaining_time":2.070993635},
{"learn":[0.1429369736],"iteration":587,"passed_time":2.948279796,"remaining_time":2.06580149},
{"learn":[0.1428231333],"iteration":588,"passed_time":2.953153622,"remaining_time":2.06068954},
{"learn":[0.1427612903],"iteration":589,"passed_time":2.958051392,"remaining_time":2.055595035},
{"learn":[0.14266305],"iteration":590,"passed_time":2.962995091,"remaining_time":2.050532982},
{"learn":[0.1426300005],"iteration":591,"passed_time":2.968000416,"remaining_time":2.0455138},
{"learn":[0.1425704165],"iteration":592,"passed_time":2.972876779,"remaining_time":2.040406153},
{"learn":[0.1424674885],"iteration":593,"passed_time":2.977649058,"remaining_time":2.035228144},
{"learn":[0.142411368],"iteration":594,"passed_time":2.982695766,"remaining_time":2.030238295},
{"learn":[0.1423795556],"iteration":595,"passed_time":2.98732675,"remaining_time":2.024966455},
{"learn":[0.1423299818],"iteration":596,"passed_time":2.992232651,"remaining_time":2.019882342},
{"learn":[0.1423246057],"iteration":597,"passed_time":2.997057423,"remaining_time":2.014744288},
{"learn":[0.1421754902],"iteration":598,"passed_time":3.001984686,"remaining_time":2.009675892},
{"learn":[0.1420959673],"iteration":599,"passed_time":3.007111757,"remaining_time":2.004741172},
{"learn":[0.1420224646],"iteration":600,"passed_time":3.012178558,"remaining_time":1.999765798},
{"learn":[0.1419068757],"iteration":601,"passed_time":3.01675058,"remaining_time":1.994463008},
{"learn":[0.1418497655],"iteration":602,"passed_time":3.021668485,"remaining_time":1.989390363},
{"learn":[0.1417656091],"iteration":603,"passed_time":3.026801822,"remaining_time":1.984459473},
{"learn":[0.1417413339],"iteration":604,"passed_time":3.031689846,"remaining_time":1.979367751},
{"learn":[0.1416864335],"iteration":605,"passed_time":3.036455728,"remaining_time":1.974197288},
{"learn":[0.1416426485],"iteration":606,"passed_time":3.041454748,"remaining_time":1.969179104},
{"learn":[0.1415711404],"iteration":607,"passed_time":3.046377674,"remaining_time":1.964111921},
{"learn":[0.1414649476],"iteration":608,"passed_time":3.051372847,"remaining_time":1.959091598},
{"learn":[0.1413584297],"iteration":609,"passed_time":3.056292043,"remaining_time":1.954022781},
{"learn":[0.1413060193],"iteration":610,"passed_time":3.061080695,"remaining_time":1.948871343},
{"learn":[0.1412898248],"iteration":611,"passed_time":3.066002684,"remaining_time":1.943805623},
{"learn":[0.1412207426],"iteration":612,"passed_time":3.070575531,"remaining_time":1.938519952},
{"learn":[0.1411704106],"iteration":613,"passed_time":3.075239296,"remaining_time":1.933293759},
{"learn":[0.141100007],"iteration":614,"passed_time":3.080629268,"remaining_time":1.928524013},
{"learn":[0.1410948451],"iteration":615,"passed_time":3.085079089,"remaining_time":1.923166185},
{"learn":[0.1410454368],"iteration":616,"passed_time":3.089924884,"remaining_time":1.9180571},
{"learn":[0.1409869744],"iteration":617,"passed_time":3.094806495,"remaining_time":1.912971005},
{"learn":[0.1409493903],"iteration":618,"passed_time":3.099444717,"remaining_time":1.907735763},
{"learn":[0.1409155329],"iteration":619,"passed_time":3.104453193,"remaining_time":1.902729376},
{"learn":[0.1408331915],"iteration":620,"passed_time":3.109173838,"remaining_time":1.897547318},
{"learn":[0.1407527952],"iteration":621,"passed_time":3.114065531,"remaining_time":1.892470693},
{"learn":[0.1406684905],"iteration":622,"passed_time":3.119408961,"remaining_time":1.887668023},
{"learn":[0.140621457],"iteration":623,"passed_time":3.124159216,"remaining_time":1.882506194},
{"learn":[0.1405366422],"iteration":624,"passed_time":3.129150739,"remaining_time":1.877490443},
{"learn":[0.1405049951],"iteration":625,"passed_time":3.133844667,"remaining_time":1.872296974},
{"learn":[0.1403548388],"iteration":626,"passed_time":3.138759992,"remaining_time":1.867236805},
{"learn":[0.140249916],"iteration":627,"passed_time":3.143590459,"remaining_time":1.862126832},
{"learn":[0.1401629233],"iteration":628,"passed_time":3.14834874,"remaining_time":1.856975171},
{"learn":[0.1400632161],"iteration":629,"passed_time":3.153211765,"remaining_time":1.851886275},
{"learn":[0.1399979251],"iteration":630,"passed_time":3.15783755,"remaining_time":1.84665936},
{"learn":[0.1399656673],"iteration":631,"passed_time":3.162701167,"remaining_time":1.841572831},
{"learn":[0.1399248841],"iteration":632,"passed_time":3.167438023,"remaining_time":1.836413514},
{"learn":[0.1398706596],"iteration":633,"passed_time":3.172235905,"remaining_time":1.831290759},
{"learn":[0.1398140278],"iteration":634,"passed_time":3.177149114,"remaining_time":1.826235317},
{"learn":[0.1397550875],"iteration":635,"passed_time":3.181894179,"remaining_time":1.82108409},
{"learn":[0.1396860209],"iteration":636,"passed_time":3.186451621,"remaining_time":1.815827219},
{"learn":[0.1395199019],"iteration":637,"passed_time":3.191207667,"remaining_time":1.810685228},
{"learn":[0.1394419957],"iteration":638,"passed_time":3.195846458,"remaining_time":1.805478202},
{"learn":[0.1394033567],"iteration":639,"passed_time":3.200756879,"remaining_time":1.800425744},
{"learn":[0.1393412],"iteration":640,"passed_time":3.205747072,"remaining_time":1.795418407},
{"learn":[0.1392509743],"iteration":641,"passed_time":3.21058705,"remaining_time":1.790327358},
{"learn":[0.1392050289],"iteration":642,"passed_time":3.215643236,"remaining_time":1.785357131},
{"learn":[0.1390845253],"iteration":643,"passed_time":3.220373112,"remaining_time":1.780206254},
{"learn":[0.1389993625],"iteration":644,"passed_time":3.22486953,"remaining_time":1.774928191},
{"learn":[0.138961696],"iteration":645,"passed_time":3.22940317,"remaining_time":1.769672945},
{"learn":[0.1388986649],"iteration":646,"passed_time":3.234355542,"remaining_time":1.764648387},
{"learn":[0.1388241729],"iteration":647,"passed_time":3.239236614,"remaining_time":1.759585321},
{"learn":[0.1387455406],"iteration":648,"passed_time":3.243938115,"remaining_time":1.754425698},
{"learn":[0.1386554451],"iteration":649,"passed_time":3.248980403,"remaining_time":1.749450986},
{"learn":[0.1385610972],"iteration":650,"passed_time":3.253721268,"remaining_time":1.744314474},
{"learn":[0.1384907773],"iteration":651,"passed_time":3.258518391,"remaining_time":1.739209203},
{"learn":[0.138460466],"iteration":652,"passed_time":3.263427376,"remaining_time":1.734164318},
{"learn":[0.1384107441],"iteration":653,"passed_time":3.268554397,"remaining_time":1.729235201},
{"learn":[0.1383504676],"iteration":654,"passed_time":3.273512703,"remaining_time":1.724216614},
{"learn":[0.1382978182],"iteration":655,"passed_time":3.27824105,"remaining_time":1.719077624},
{"learn":[0.1382236974],"iteration":656,"passed_time":3.283216211,"remaining_time":1.714068738},
{"learn":[0.1381862285],"iteration":657,"passed_time":3.287939375,"remaining_time":1.708928976},
{"learn":[0.1380985923],"iteration":658,"passed_time":3.292808265,"remaining_time":1.703865885},
{"learn":[0.1379750382],"iteration":659,"passed_time":3.297652221,"remaining_time":1.698790538},
{"learn":[0.1378922929],"iteration":660,"passed_time":3.302668458,"remaining_time":1.693804247},
{"learn":[0.1378084911],"iteration":661,"passed_time":3.307578652,"remaining_time":1.688763723},
{"learn":[0.1377455827],"iteration":662,"passed_time":3.312563184,"remaining_time":1.683761377},
{"learn":[0.1376739434],"iteration":663,"passed_time":3.317135882,"remaining_time":1.678550687},
{"learn":[0.1375767095],"iteration":664,"passed_time":3.321756471,"remaining_time":1.673366042},
{"learn":[0.1375117574],"iteration":665,"passed_time":3.326462716,"remaining_time":1.668226047},
{"learn":[0.1373524401],"iteration":666,"passed_time":3.331358718,"remaining_time":1.663182089},
{"learn":[0.1372906384],"iteration":667,"passed_time":3.336034034,"remaining_time":1.658028891},
{"learn":[0.1372247466],"iteration":668,"passed_time":3.340785989,"remaining_time":1.652915041},
{"learn":[0.1371502877],"iteration":669,"passed_time":3.345407462,"remaining_time":1.647738004},
{"learn":[0.1371374241],"iteration":670,"passed_time":3.350249092,"remaining_time":1.642670568},
{"learn":[0.1370457396],"iteration":671,"passed_time":3.355110453,"remaining_time":1.637613435},
{"learn":[0.136960998],"iteration":672,"passed_time":3.359880039,"remaining_time":1.632512292},
{"learn":[0.1368744753],"iteration":673,"passed_time":3.364619368,"remaining_time":1.627397498},
{"learn":[0.1368200687],"iteration":674,"passed_time":3.369429412,"remaining_time":1.622317865},
{"learn":[0.1367579618],"iteration":675,"passed_time":3.374486643,"remaining_time":1.617357503},
{"learn":[0.136674671],"iteration":676,"passed_time":3.379289342,"remaining_time":1.612275417},
{"learn":[0.1366553269],"iteration":677,"passed_time":3.383954929,"remaining_time":1.607129037},
{"learn":[0.1365844956],"iteration":678,"passed_time":3.388351713,"remaining_time":1.601856995},
{"learn":[0.1364447141],"iteration":679,"passed_time":3.393157308,"remaining_time":1.59677991},
{"learn":[0.136427571],"iteration":680,"passed_time":3.397770855,"remaining_time":1.591613661},
{"learn":[0.1363457643],"iteration":681,"passed_time":3.402647036,"remaining_time":1.586571492},
{"learn":[0.1362729211],"iteration":682,"passed_time":3.407501335,"remaining_time":1.581519653},
{"learn":[0.1362338609],"iteration":683,"passed_time":3.412158536,"remaining_time":1.576377335},
{"learn":[0.1361521373],"iteration":684,"passed_time":3.417050752,"remaining_time":1.571344506},
{"learn":[0.1360285664],"iteration":685,"passed_time":3.421874143,"remaining_time":1.566280584},
{"learn":[0.1359561917],"iteration":686,"passed_time":3.426643802,"remaining_time":1.561192882},
{"learn":[0.1358175471],"iteration":687,"passed_time":3.431911729,"remaining_time":1.556332063},
{"learn":[0.1357319374],"iteration":688,"passed_time":3.436827879,"remaining_time":1.551311278},
{"learn":[0.1356685266],"iteration":689,"passed_time":3.441855242,"remaining_time":1.546340761},
{"learn":[0.1355870418],"iteration":690,"passed_time":3.446913134,"remaining_time":1.541383731},
{"learn":[0.1355138764],"iteration":691,"passed_time":3.451880687,"remaining_time":1.536386202},
{"learn":[0.1353976347],"iteration":692,"passed_time":3.456963457,"remaining_time":1.5314398},
{"learn":[0.1353207514],"iteration":693,"passed_time":3.461957354,"remaining_time":1.526453819},
{"learn":[0.1352540183],"iteration":694,"passed_time":3.466706968,"remaining_time":1.521360612},
{"learn":[0.1352338988],"iteration":695,"passed_time":3.471388517,"remaining_time":1.516238663},
{"learn":[0.1351252695],"iteration":696,"passed_time":3.47664292,"remaining_time":1.511367008},
{"learn":[0.1350568283],"iteration":697,"passed_time":3.481712591,"remaining_time":1.50641433},
{"learn":[0.1349527177],"iteration":698,"passed_time":3.486866421,"remaining_time":1.501497558},
{"learn":[0.1349058404],"iteration":699,"passed_time":3.491794409,"remaining_time":1.496483318},
{"learn":[0.1348128665],"iteration":700,"passed_time":3.496666698,"remaining_time":1.491445568},
{"learn":[0.1347400316],"iteration":701,"passed_time":3.501542512,"remaining_time":1.486409784},
{"learn":[0.1346268915],"iteration":702,"passed_time":3.506522312,"remaining_time":1.481418388},
{"learn":[0.1345094195],"iteration":703,"passed_time":3.511318663,"remaining_time":1.476349892},
{"learn":[0.13440351],"iteration":704,"passed_time":3.516200999,"remaining_time":1.471318149},
{"learn":[0.1343561298],"iteration":705,"passed_time":3.521176872,"remaining_time":1.46632578},
{"learn":[0.1342475717],"iteration":706,"passed_time":3.525890226,"remaining_time":1.461224662},
{"learn":[0.1341748853],"iteration":707,"passed_time":3.530893154,"remaining_time":1.456244069},
{"learn":[0.1340878924],"iteration":708,"passed_time":3.535563399,"remaining_time":1.451126868},
{"learn":[0.1339978756],"iteration":709,"passed_time":3.540481686,"remaining_time":1.446112238},
{"learn":[0.1339056468],"iteration":710,"passed_time":3.545497979,"remaining_time":1.441137716},
{"learn":[0.133782884],"iteration":711,"passed_time":3.550363711,"remaining_time":1.436102175},
{"learn":[0.1337123293],"iteration":712,"passed_time":3.555456054,"remaining_time":1.431158327},
{"learn":[0.1335903085],"iteration":713,"passed_time":3.560361942,"remaining_time":1.426139377},
{"learn":[0.1334992423],"iteration":714,"passed_time":3.565620732,"remaining_time":1.421261411},
{"learn":[0.1334409534],"iteration":715,"passed_time":3.570786449,"remaining_time":1.416345463},
{"learn":[0.1333228823],"iteration":716,"passed_time":3.575513052,"remaining_time":1.4112555},
{"learn":[0.1332673804],"iteration":717,"passed_time":3.580358001,"remaining_time":1.406213031},
{"learn":[0.1331507277],"iteration":718,"passed_time":3.585329006,"remaining_time":1.401220376},
{"learn":[0.1330710075],"iteration":719,"passed_time":3.590008669,"remaining_time":1.396114482},
{"learn":[0.1329950806],"iteration":720,"passed_time":3.594898091,"remaining_time":1.39109094},
{"learn":[0.1329060894],"iteration":721,"passed_time":3.599529455,"remaining_time":1.385968405},
{"learn":[0.1328501502],"iteration":722,"passed_time":3.60437601,"remaining_time":1.380929675},
{"learn":[0.132750047],"iteration":723,"passed_time":3.60938549,"remaining_time":1.375953585},
{"learn":[0.1326612567],"iteration":724,"passed_time":3.614088438,"remaining_time":1.370861132},
{"learn":[0.132595868],"iteration":725,"passed_time":3.619043529,"remaining_time":1.365864913},
{"learn":[0.1325342144],"iteration":726,"passed_time":3.624133762,"remaining_time":1.360919556},
{"learn":[0.1324604899],"iteration":727,"passed_time":3.629055537,"remaining_time":1.35591086},
{"learn":[0.1323879354],"iteration":728,"passed_time":3.634131038,"remaining_time":1.350959549},
{"learn":[0.1323353854],"iteration":729,"passed_time":3.638974255,"remaining_time":1.345921985},
{"learn":[0.1322662612],"iteration":730,"passed_time":3.64444345,"remaining_time":1.341115305},
{"learn":[0.1322029085],"iteration":731,"passed_time":3.649573399,"remaining_time":1.33618261},
{"learn":[0.1321324074],"iteration":732,"passed_time":3.654978103,"remaining_time":1.331349459},
{"learn":[0.1320773341],"iteration":733,"passed_time":3.660569643,"remaining_time":1.326582459},
{"learn":[0.1319828956],"iteration":734,"passed_time":3.665448776,"remaining_time":1.321556361},
{"learn":[0.1318815964],"iteration":735,"passed_time":3.67068745,"remaining_time":1.316659629},
{"learn":[0.1318443424],"iteration":736,"passed_time":3.675811697,"remaining_time":1.311721135},
{"learn":[0.1317771228],"iteration":737,"passed_time":3.681114779,"remaining_time":1.306845626},
{"learn":[0.1316830798],"iteration":738,"passed_time":3.686329975,"remaining_time":1.301937921},
{"learn":[0.1316340743],"iteration":739,"passed_time":3.691266836,"remaining_time":1.296931591},
{"learn":[0.1315909491],"iteration":740,"passed_time":3.696354536,"remaining_time":1.291978171},
{"learn":[0.1315526964],"iteration":741,"passed_time":3.701832117,"remaining_time":1.287159954},
{"learn":[0.1315059257],"iteration":742,"passed_time":3.706909499,"remaining_time":1.282201536},
{"learn":[0.1314468447],"iteration":743,"passed_time":3.71549245,"remaining_time":1.278449015},
{"learn":[0.1314285475],"iteration":744,"passed_time":3.72063999,"remaining_time":1.273507647},
{"learn":[0.1313916473],"iteration":745,"passed_time":3.726222107,"remaining_time":1.268713693},
{"learn":[0.1313283939],"iteration":746,"passed_time":3.731078278,"remaining_time":1.263671759},
{"learn":[0.1312853676],"iteration":747,"passed_time":3.736571026,"remaining_time":1.258844784},
{"learn":[0.1312406012],"iteration":748,"passed_time":3.741292922,"remaining_time":1.253757708},
{"learn":[0.1311947293],"iteration":749,"passed_time":3.745992822,"remaining_time":1.248664274},
{"learn":[0.1311560396],"iteration":750,"passed_time":3.750932943,"remaining_time":1.243651535},
{"learn":[0.1310757243],"iteration":751,"passed_time":3.755899362,"remaining_time":1.238647662},
{"learn":[0.1310091644],"iteration":752,"passed_time":3.761229425,"remaining_time":1.233763171},
{"learn":[0.1309743427],"iteration":753,"passed_time":3.766229078,"remaining_time":1.228769699},
{"learn":[0.1309195662],"iteration":754,"passed_time":3.771089273,"remaining_time":1.223730956},
{"learn":[0.13083574],"iteration":755,"passed_time":3.776163224,"remaining_time":1.218761675},
{"learn":[0.1307331616],"iteration":756,"passed_time":3.780904572,"remaining_time":1.213685351},
{"learn":[0.1307153753],"iteration":757,"passed_time":3.785666415,"remaining_time":1.208616454},
{"learn":[0.1306603187],"iteration":758,"passed_time":3.790788709,"remaining_time":1.203662818},
{"learn":[0.1306220833],"iteration":759,"passed_time":3.795949098,"remaining_time":1.198720768},
{"learn":[0.1305759976],"iteration":760,"passed_time":3.800687152,"remaining_time":1.193645505},
{"learn":[0.1305168756],"iteration":761,"passed_time":3.80555625,"remaining_time":1.188612057},
{"learn":[0.1304995923],"iteration":762,"passed_time":3.810561661,"remaining_time":1.183621381},
{"learn":[0.130449557],"iteration":763,"passed_time":3.815256515,"remaining_time":1.178534735},
{"learn":[0.1303124877],"iteration":764,"passed_time":3.820027311,"remaining_time":1.173472442},
{"learn":[0.1302787873],"iteration":765,"passed_time":3.824809393,"remaining_time":1.168414358},
{"learn":[0.1301972367],"iteration":766,"passed_time":3.829317734,"remaining_time":1.163273836},
{"learn":[0.1301453049],"iteration":767,"passed_time":3.833982872,"remaining_time":1.158182326},
{"learn":[0.1300905531],"iteration":768,"passed_time":3.838595062,"remaining_time":1.15307602},
{"learn":[0.1300201673],"iteration":769,"passed_time":3.843456898,"remaining_time":1.148045567},
{"learn":[0.1299951168],"iteration":770,"passed_time":3.84807207,"remaining_time":1.142942288},
{"learn":[0.1299099963],"iteration":771,"passed_time":3.852994847,"remaining_time":1.137931121},
{"learn":[0.1298467514],"iteration":772,"passed_time":3.857885803,"remaining_time":1.132910837},
{"learn":[0.1298148648],"iteration":773,"passed_time":3.862659904,"remaining_time":1.127856768},
{"learn":[0.129716391],"iteration":774,"passed_time":3.867686918,"remaining_time":1.122876847},
{"learn":[0.1296187601],"iteration":775,"passed_time":3.872681861,"remaining_time":1.117887547},
{"learn":[0.1295452574],"iteration":776,"passed_time":3.877612974,"remaining_time":1.112879914},
{"learn":[0.1294564674],"iteration":777,"passed_time":3.882529764,"remaining_time":1.10786839},
{"learn":[0.1293810186],"iteration":778,"passed_time":3.887252487,"remaining_time":1.102802054},
{"learn":[0.1292834877],"iteration":779,"passed_time":3.89211242,"remaining_time":1.097775298},
{"learn":[0.129211568],"iteration":780,"passed_time":3.897096076,"remaining_time":1.092783663},
{"learn":[0.1291570964],"iteration":781,"passed_time":3.902019175,"remaining_time":1.087775166},
{"learn":[0.1290826371],"iteration":782,"passed_time":3.906802654,"remaining_time":1.082728194},
{"learn":[0.1290660962],"iteration":783,"passed_time":3.9115505,"remaining_time":1.077672076},
{"learn":[0.1290325356],"iteration":784,"passed_time":3.916082874,"remaining_time":1.07255773},
{"learn":[0.1289645407],"iteration":785,"passed_time":3.920510737,"remaining_time":1.067416409},
{"learn":[0.1288409691],"iteration":786,"passed_time":3.925116828,"remaining_time":1.062325139},
{"learn":[0.1287672271],"iteration":787,"passed_time":3.929694671,"remaining_time":1.0572275},
{"learn":[0.1287192123],"iteration":788,"passed_time":3.934330617,"remaining_time":1.052146717},
{"learn":[0.1286067554],"iteration":789,"passed_time":3.939154442,"remaining_time":1.047117003},
{"learn":[0.1285295832],"iteration":790,"passed_time":3.944005454,"remaining_time":1.042094994},
{"learn":[0.1284335851],"iteration":791,"passed_time":3.948975072,"remaining_time":1.037104564},
{"learn":[0.1283441589],"iteration":792,"passed_time":3.953674844,"remaining_time":1.032043749},
{"learn":[0.1283282444],"iteration":793,"passed_time":3.958485043,"remaining_time":1.027012492},
{"learn":[0.1282583535],"iteration":794,"passed_time":3.963491108,"remaining_time":1.022032298},
{"learn":[0.1282084256],"iteration":795,"passed_time":3.968278976,"remaining_time":1.016996119},
{"learn":[0.1281378005],"iteration":796,"passed_time":3.97320019,"remaining_time":1.011994528},
{"learn":[0.1280937179],"iteration":797,"passed_time":3.978215203,"remaining_time":1.007016881},
{"learn":[0.1279930029],"iteration":798,"passed_time":3.982979601,"remaining_time":1.001976095},
{"learn":[0.1279082782],"iteration":799,"passed_time":3.987924427,"remaining_time":0.9969811068},
{"learn":[0.1278471111],"iteration":800,"passed_time":3.992909685,"remaining_time":0.9919962888},
{"learn":[0.1278146966],"iteration":801,"passed_time":3.99775125,"remaining_time":0.9869759945},
{"learn":[0.1277270329],"iteration":802,"passed_time":4.002630884,"remaining_time":0.9819654846},
{"learn":[0.1276634663],"iteration":803,"passed_time":4.007376258,"remaining_time":0.9769225703},
{"learn":[0.1275993884],"iteration":804,"passed_time":4.012280374,"remaining_time":0.9719188485},
{"learn":[0.1275132202],"iteration":805,"passed_time":4.017001019,"remaining_time":0.966871213},
{"learn":[0.1274109471],"iteration":806,"passed_time":4.021854898,"remaining_time":0.961856252},
{"learn":[0.1273442883],"iteration":807,"passed_time":4.026619977,"remaining_time":0.9568205886},
{"learn":[0.127266068],"iteration":808,"passed_time":4.031322734,"remaining_time":0.9517708803},
{"learn":[0.1271981231],"iteration":809,"passed_time":4.036188995,"remaining_time":0.9467603816},
{"learn":[0.127117892],"iteration":810,"passed_time":4.04077387,"remaining_time":0.9416846627},
{"learn":[0.1270597759],"iteration":811,"passed_time":4.045639357,"remaining_time":0.936675122},
{"learn":[0.1270052384],"iteration":812,"passed_time":4.051273096,"remaining_time":0.9318426432},
{"learn":[0.1269681489],"iteration":813,"passed_time":4.056365327,"remaining_time":0.9268844605},
{"learn":[0.1269276459],"iteration":814,"passed_time":4.06104632,"remaining_time":0.9218326003},
{"learn":[0.1269130345],"iteration":815,"passed_time":4.065994426,"remaining_time":0.9168418804},
{"learn":[0.1268691169],"iteration":816,"passed_time":4.070770847,"remaining_time":0.9118128091},
{"learn":[0.126802491],"iteration":817,"passed_time":4.075532965,"remaining_time":0.9067811731},
{"learn":[0.1267702831],"iteration":818,"passed_time":4.080489501,"remaining_time":0.9017931621},
{"learn":[0.12670173],"iteration":819,"passed_time":4.085319285,"remaining_time":0.8967774041},
{"learn":[0.1266211516],"iteration":820,"passed_time":4.090248599,"remaining_time":0.8917837993},
{"learn":[0.1265906999],"iteration":821,"passed_time":4.09513096,"remaining_time":0.8867801835},
{"learn":[0.1265416623],"iteration":822,"passed_time":4.100103375,"remaining_time":0.8817962302},
{"learn":[0.1264941584],"iteration":823,"passed_time":4.104889093,"remaining_time":0.8767724276},
{"learn":[0.126436512],"iteration":824,"passed_time":4.109567134,"remaining_time":0.8717263617},
{"learn":[0.1263232071],"iteration":825,"passed_time":4.114365771,"remaining_time":0.8667065911},
{"learn":[0.126217587],"iteration":826,"passed_time":4.119158375,"remaining_time":0.8616860929},
{"learn":[0.1261695802],"iteration":827,"passed_time":4.123903056,"remaining_time":0.8566561903},
{"learn":[0.1261273942],"iteration":828,"passed_time":4.128589443,"remaining_time":0.8516149514},
{"learn":[0.1260545682],"iteration":829,"passed_time":4.133316377,"remaining_time":0.8465828724},
{"learn":[0.1259841248],"iteration":830,"passed_time":4.138083472,"remaining_time":0.8415596952},
{"learn":[0.1259353594],"iteration":831,"passed_time":4.142794253,"remaining_time":0.8365257626},
{"learn":[0.1258899593],"iteration":832,"passed_time":4.147711241,"remaining_time":0.8315339462},
{"learn":[0.1258413834],"iteration":833,"passed_time":4.152603265,"remaining_time":0.8265373404},
{"learn":[0.1257560731],"iteration":834,"passed_time":4.157501206,"remaining_time":0.8215421544},
{"learn":[0.1256736868],"iteration":835,"passed_time":4.162225717,"remaining_time":0.8165131789},
{"learn":[0.1255656921],"iteration":836,"passed_time":4.166913553,"remaining_time":0.8114777887},
{"learn":[0.1255153848],"iteration":837,"passed_time":4.171853668,"remaining_time":0.8064919979},
{"learn":[0.1254431434],"iteration":838,"passed_time":4.176742825,"remaining_time":0.8014965373},
{"learn":[0.1254276085],"iteration":839,"passed_time":4.181604181,"remaining_time":0.7964960344},
{"learn":[0.1253709686],"iteration":840,"passed_time":4.186269848,"remaining_time":0.7914588654},
{"learn":[0.1253355854],"iteration":841,"passed_time":4.191305643,"remaining_time":0.7864920327},
{"learn":[0.1252541745],"iteration":842,"passed_time":4.197007205,"remaining_time":0.7816490287},
{"learn":[0.1251882989],"iteration":843,"passed_time":4.202101722,"remaining_time":0.7766917875},
{"learn":[0.1251409106],"iteration":844,"passed_time":4.206836739,"remaining_time":0.7716682775},
{"learn":[0.1250770634],"iteration":845,"passed_time":4.211918194,"remaining_time":0.7667085128},
{"learn":[0.1249594628],"iteration":846,"passed_time":4.216831869,"remaining_time":0.7617181535},
{"learn":[0.1248421258],"iteration":847,"passed_time":4.221423881,"remaining_time":0.7566703183},
{"learn":[0.1247504074],"iteration":848,"passed_time":4.226318257,"remaining_time":0.7516773342},
{"learn":[0.1246488609],"iteration":849,"passed_time":4.231220446,"remaining_time":0.7466859611},
{"learn":[0.1246140473],"iteration":850,"passed_time":4.236267677,"remaining_time":0.7417201926},
{"learn":[0.1245441892],"iteration":851,"passed_time":4.240918948,"remaining_time":0.7366854511},
{"learn":[0.1244482199],"iteration":852,"passed_time":4.245778122,"remaining_time":0.7316874372},
{"learn":[0.1243719136],"iteration":853,"passed_time":4.250999567,"remaining_time":0.7267516824},
{"learn":[0.1243060714],"iteration":854,"passed_time":4.255871763,"remaining_time":0.72175603},
{"learn":[0.1242600847],"iteration":855,"passed_time":4.260432965,"remaining_time":0.7167083493},
{"learn":[0.124231315],"iteration":856,"passed_time":4.26519259,"remaining_time":0.7116949129},
{"learn":[0.1241905561],"iteration":857,"passed_time":4.269869076,"remaining_time":0.7066683086},
{"learn":[0.1240919697],"iteration":858,"passed_time":4.274919246,"remaining_time":0.7017038576},
{"learn":[0.1240080114],"iteration":859,"passed_time":4.279600359,"remaining_time":0.6966791283},
{"learn":[0.1239233607],"iteration":860,"passed_time":4.284335173,"remaining_time":0.6916638665},
{"learn":[0.1238608903],"iteration":861,"passed_time":4.289232693,"remaining_time":0.6866753035},
{"learn":[0.1238160664],"iteration":862,"passed_time":4.294138448,"remaining_time":0.6816882589},
{"learn":[0.1236482242],"iteration":863,"passed_time":4.298920972,"remaining_time":0.6766820048},
{"learn":[0.1235567945],"iteration":864,"passed_time":4.303587823,"remaining_time":0.6716582151},
{"learn":[0.1235100572],"iteration":865,"passed_time":4.308259816,"remaining_time":0.6666360454},
{"learn":[0.1234458475],"iteration":866,"passed_time":4.312808019,"remaining_time":0.6615956938},
{"learn":[0.123335437],"iteration":867,"passed_time":4.317710738,"remaining_time":0.6566103887},
{"learn":[0.1232405276],"iteration":868,"passed_time":4.322568888,"remaining_time":0.6516185551},
{"learn":[0.1232258006],"iteration":869,"passed_time":4.327795168,"remaining_time":0.6466820366},
{"learn":[0.1231936916],"iteration":870,"passed_time":4.332676399,"remaining_time":0.6416937492},
{"learn":[0.1231189719],"iteration":871,"passed_time":4.337967097,"remaining_time":0.6367658125},
{"learn":[0.1230626287],"iteration":872,"passed_time":4.342917668,"remaining_time":0.6317875646},
{"learn":[0.1229458939],"iteration":873,"passed_time":4.347687247,"remaining_time":0.6267832873},
{"learn":[0.1228467791],"iteration":874,"passed_time":4.352979616,"remaining_time":0.6218542309},
{"learn":[0.1228036373],"iteration":875,"passed_time":4.35812037,"remaining_time":0.6169028834},
{"learn":[0.1227094371],"iteration":876,"passed_time":4.363016612,"remaining_time":0.611916811},
{"learn":[0.1226503645],"iteration":877,"passed_time":4.367818062,"remaining_time":0.6069177717},
{"learn":[0.1225645092],"iteration":878,"passed_time":4.372889839,"remaining_time":0.6019563942},
{"learn":[0.1224938418],"iteration":879,"passed_time":4.377927276,"remaining_time":0.5969900831},
{"learn":[0.1224088609],"iteration":880,"passed_time":4.382928142,"remaining_time":0.5920186707},
{"learn":[0.1223369416],"iteration":881,"passed_time":4.387873035,"remaining_time":0.5870397031},
{"learn":[0.1222630266],"iteration":882,"passed_time":4.392805238,"remaining_time":0.5820591312},
{"learn":[0.1221924264],"iteration":883,"passed_time":4.397857738,"remaining_time":0.5770944543},
{"learn":[0.1221021517],"iteration":884,"passed_time":4.402716896,"remaining_time":0.5721044554},
{"learn":[0.1220300836],"iteration":885,"passed_time":4.407383468,"remaining_time":0.5670899721},
{"learn":[0.1219746061],"iteration":886,"passed_time":4.411769906,"remaining_time":0.5620405855},
{"learn":[0.1219311006],"iteration":887,"passed_time":4.416500494,"remaining_time":0.5570360983},
{"learn":[0.1218651839],"iteration":888,"passed_time":4.421372246,"remaining_time":0.552049853},
{"learn":[0.1218212012],"iteration":889,"passed_time":4.426302499,"remaining_time":0.5470710954},
{"learn":[0.1217582777],"iteration":890,"passed_time":4.431256981,"remaining_time":0.5420954107},
{"learn":[0.121744235],"iteration":891,"passed_time":4.435700522,"remaining_time":0.5370579108},
{"learn":[0.1216939934],"iteration":892,"passed_time":4.440658512,"remaining_time":0.5320833827},
{"learn":[0.1216415752],"iteration":893,"passed_time":4.445534001,"remaining_time":0.5270991098},
{"learn":[0.1215789569],"iteration":894,"passed_time":4.450571791,"remaining_time":0.5221341208},
{"learn":[0.1215305296],"iteration":895,"passed_time":4.455260963,"remaining_time":0.5171285047},
{"learn":[0.1214740546],"iteration":896,"passed_time":4.460009115,"remaining_time":0.5121303666},
{"learn":[0.1214308631],"iteration":897,"passed_time":4.464755468,"remaining_time":0.507132581},
{"learn":[0.1213813307],"iteration":898,"passed_time":4.469060792,"remaining_time":0.5020858065},
{"learn":[0.1212667237],"iteration":899,"passed_time":4.47383731,"remaining_time":0.4970930345},
{"learn":[0.1212161029],"iteration":900,"passed_time":4.478777926,"remaining_time":0.4921187732},
{"learn":[0.1211840762],"iteration":901,"passed_time":4.483752828,"remaining_time":0.4871483117},
{"learn":[0.1211284255],"iteration":902,"passed_time":4.488467621,"remaining_time":0.4821498995},
{"learn":[0.121089621],"iteration":903,"passed_time":4.493590815,"remaining_time":0.4771954847},
{"learn":[0.1209794992],"iteration":904,"passed_time":4.498363104,"remaining_time":0.4722038617},
{"learn":[0.1208992098],"iteration":905,"passed_time":4.503465417,"remaining_time":0.4672469638},
{"learn":[0.1208626315],"iteration":906,"passed_time":4.508506224,"remaining_time":0.4622834387},
{"learn":[0.1207794299],"iteration":907,"passed_time":4.513605572,"remaining_time":0.4573256747},
{"learn":[0.1207316949],"iteration":908,"passed_time":4.518351522,"remaining_time":0.4523322206},
{"learn":[0.1206998251],"iteration":909,"passed_time":4.523153679,"remaining_time":0.4473448694},
{"learn":[0.1206615487],"iteration":910,"passed_time":4.527827439,"remaining_time":0.442345381},
{"learn":[0.1205843025],"iteration":911,"passed_time":4.532750289,"remaining_time":0.437370642},
{"learn":[0.120567539],"iteration":912,"passed_time":4.53742219,"remaining_time":0.4323721035},
{"learn":[0.1205548817],"iteration":913,"passed_time":4.542116195,"remaining_time":0.4273763597},
{"learn":[0.1204788885],"iteration":914,"passed_time":4.5471648,"remaining_time":0.4224142164},
{"learn":[0.1203902305],"iteration":915,"passed_time":4.551954315,"remaining_time":0.417428125},
{"learn":[0.1203217454],"iteration":916,"passed_time":4.556991743,"remaining_time":0.4124649015},
{"learn":[0.1202911947],"iteration":917,"passed_time":4.561810545,"remaining_time":0.4074819877},
{"learn":[0.1202194399],"iteration":918,"passed_time":4.566511568,"remaining_time":0.4024890501},
{"learn":[0.1201609279],"iteration":919,"passed_time":4.571505671,"remaining_time":0.3975222323},
{"learn":[0.1200412981],"iteration":920,"passed_time":4.576511094,"remaining_time":0.3925563262},
{"learn":[0.1200016774],"iteration":921,"passed_time":4.581316285,"remaining_time":0.387573395},
{"learn":[0.1199604566],"iteration":922,"passed_time":4.586244809,"remaining_time":0.3826011379},
{"learn":[0.1199226913],"iteration":923,"passed_time":4.591418314,"remaining_time":0.3776491254},
{"learn":[0.1198676507],"iteration":924,"passed_time":4.596798661,"remaining_time":0.3727134049},
{"learn":[0.1198170299],"iteration":925,"passed_time":4.601925343,"remaining_time":0.3677564529},
{"learn":[0.119766673],"iteration":926,"passed_time":4.607155752,"remaining_time":0.362807303},
{"learn":[0.1197234405],"iteration":927,"passed_time":4.61225168,"remaining_time":0.3578471131},
{"learn":[0.1196655636],"iteration":928,"passed_time":4.617350219,"remaining_time":0.3528868305},
{"learn":[0.1196385588],"iteration":929,"passed_time":4.622226116,"remaining_time":0.3479094926},
{"learn":[0.1195884081],"iteration":930,"passed_time":4.627123709,"remaining_time":0.3429339806},
{"learn":[0.119551483],"iteration":931,"passed_time":4.63335971,"remaining_time":0.3380562879},
{"learn":[0.1194715076],"iteration":932,"passed_time":4.638332967,"remaining_time":0.333085004},
{"learn":[0.1194382936],"iteration":933,"passed_time":4.643254155,"remaining_time":0.3281100367},
{"learn":[0.1193820077],"iteration":934,"passed_time":4.648274636,"remaining_time":0.323142087},
{"learn":[0.1193203712],"iteration":935,"passed_time":4.6532322,"remaining_time":0.3181697231},
{"learn":[0.1192848651],"iteration":936,"passed_time":4.65804322,"remaining_time":0.3131875377},
{"learn":[0.1192246711],"iteration":937,"passed_time":4.66408447,"remaining_time":0.3082870332},
{"learn":[0.1191581934],"iteration":938,"passed_time":4.670877432,"remaining_time":0.3034329322},
{"learn":[0.1190961859],"iteration":939,"passed_time":4.675711308,"remaining_time":0.298449658},
{"learn":[0.1190397025],"iteration":940,"passed_time":4.681127371,"remaining_time":0.2935032039},
{"learn":[0.1189881419],"iteration":941,"passed_time":4.686512791,"remaining_time":0.2885538661},
{"learn":[0.1189437465],"iteration":942,"passed_time":4.691369149,"remaining_time":0.2835716241},
{"learn":[0.1188662942],"iteration":943,"passed_time":4.696355088,"remaining_time":0.2785973357},
{"learn":[0.1188282901],"iteration":944,"passed_time":4.701214564,"remaining_time":0.2736156624},
{"learn":[0.118781446],"iteration":945,"passed_time":4.706003519,"remaining_time":0.268630222},
{"learn":[0.1186802864],"iteration":946,"passed_time":4.711353388,"remaining_time":0.2636765888},
{"learn":[0.1186322465],"iteration":947,"passed_time":4.715960708,"remaining_time":0.258681389},
{"learn":[0.1185688768],"iteration":948,"passed_time":4.721016269,"remaining_time":0.2537110956},
{"learn":[0.1184980695],"iteration":949,"passed_time":4.725797377,"remaining_time":0.2487261777},
{"learn":[0.1184020229],"iteration":950,"passed_time":4.730522465,"remaining_time":0.2437388021},
{"learn":[0.1183097446],"iteration":951,"passed_time":4.735293107,"remaining_time":0.2387542743},
{"learn":[0.1182656378],"iteration":952,"passed_time":4.740019565,"remaining_time":0.2337680163},
{"learn":[0.1182367446],"iteration":953,"passed_time":4.744690431,"remaining_time":0.2287796225},
{"learn":[0.118170111],"iteration":954,"passed_time":4.749773363,"remaining_time":0.2238113103},
{"learn":[0.1181130256],"iteration":955,"passed_time":4.75469566,"remaining_time":0.2188353651},
{"learn":[0.1180915043],"iteration":956,"passed_time":4.759679919,"remaining_time":0.2138623161},
{"learn":[0.1180399929],"iteration":957,"passed_time":4.764794675,"remaining_time":0.2088949649},
{"learn":[0.1179552185],"iteration":958,"passed_time":4.769644161,"remaining_time":0.2039159652},
{"learn":[0.1179112357],"iteration":959,"passed_time":4.774621426,"remaining_time":0.1989425594},
{"learn":[0.1178648613],"iteration":960,"passed_time":4.779458367,"remaining_time":0.1939634509},
{"learn":[0.1178093009],"iteration":961,"passed_time":4.784121885,"remaining_time":0.1889777876},
{"learn":[0.1177410015],"iteration":962,"passed_time":4.789639666,"remaining_time":0.1840256154},
{"learn":[0.1176247027],"iteration":963,"passed_time":4.794730021,"remaining_time":0.1790563078},
{"learn":[0.1175808924],"iteration":964,"passed_time":4.799687795,"remaining_time":0.1740819407},
{"learn":[0.1175102927],"iteration":965,"passed_time":4.804567109,"remaining_time":0.1691048465},
{"learn":[0.117413042],"iteration":966,"passed_time":4.809470257,"remaining_time":0.1641287678},
{"learn":[0.1173746992],"iteration":967,"passed_time":4.814190874,"remaining_time":0.1591468058},
{"learn":[0.1172962076],"iteration":968,"passed_time":4.818901735,"remaining_time":0.154165071},
{"learn":[0.1172505014],"iteration":969,"passed_time":4.823806659,"remaining_time":0.1491898967},
{"learn":[0.1172062784],"iteration":970,"passed_time":4.828928709,"remaining_time":0.1442213518},
{"learn":[0.1170961555],"iteration":971,"passed_time":4.833740021,"remaining_time":0.1392435397},
{"learn":[0.1170589921],"iteration":972,"passed_time":4.838349415,"remaining_time":0.1342604668},
{"learn":[0.1170174413],"iteration":973,"passed_time":4.843417768,"remaining_time":0.1292904127},
{"learn":[0.1169182034],"iteration":974,"passed_time":4.848025748,"remaining_time":0.1243083525},
{"learn":[0.1168651087],"iteration":975,"passed_time":4.852864313,"remaining_time":0.119332729},
{"learn":[0.1168141308],"iteration":976,"passed_time":4.857895167,"remaining_time":0.1143619128},
{"learn":[0.1167435731],"iteration":977,"passed_time":4.862545316,"remaining_time":0.10938241},
{"learn":[0.1167099222],"iteration":978,"passed_time":4.867293126,"remaining_time":0.1044056748},
{"learn":[0.1165740151],"iteration":979,"passed_time":4.872014515,"remaining_time":0.09942886765},
{"learn":[0.1165176717],"iteration":980,"passed_time":4.87670078,"remaining_time":0.09445190094},
{"learn":[0.1164842018],"iteration":981,"passed_time":4.881503256,"remaining_time":0.08947765643},
{"learn":[0.1164188947],"iteration":982,"passed_time":4.886322919,"remaining_time":0.08450405862},
{"learn":[0.116354125],"iteration":983,"passed_time":4.891073041,"remaining_time":0.07952964294},
{"learn":[0.1162835159],"iteration":984,"passed_time":4.896037107,"remaining_time":0.07455894071},
{"learn":[0.1162721204],"iteration":985,"passed_time":4.90087863,"remaining_time":0.06958651198},
{"learn":[0.1161997544],"iteration":986,"passed_time":4.905889556,"remaining_time":0.06461657977},
{"learn":[0.1161403262],"iteration":987,"passed_time":4.910942616,"remaining_time":0.0596470763},
{"learn":[0.1161120677],"iteration":988,"passed_time":4.915778506,"remaining_time":0.05467498844},
{"learn":[0.1160204904],"iteration":989,"passed_time":4.920567432,"remaining_time":0.04970270134},
{"learn":[0.115988604],"iteration":990,"passed_time":4.925672417,"remaining_time":0.04473365465},
{"learn":[0.115963652],"iteration":991,"passed_time":4.93069537,"remaining_time":0.03976367234},
{"learn":[0.1158842537],"iteration":992,"passed_time":4.935844211,"remaining_time":0.03479447077},
{"learn":[0.1157924694],"iteration":993,"passed_time":4.940731843,"remaining_time":0.02982333104},
{"learn":[0.1157197914],"iteration":994,"passed_time":4.945651136,"remaining_time":0.02485251827},
{"learn":[0.1156536768],"iteration":995,"passed_time":4.950530231,"remaining_time":0.01988164752},
{"learn":[0.1155781614],"iteration":996,"passed_time":4.955417429,"remaining_time":0.01491098524},
{"learn":[0.1155079902],"iteration":997,"passed_time":4.960369796,"remaining_time":0.009940620834},
{"learn":[0.1154666876],"iteration":998,"passed_time":4.965312794,"remaining_time":0.004970283077},
{"learn":[0.1154111111],"iteration":999,"passed_time":4.970518343,"remaining_time":0}
]}